{
  "region": {
    "code": "22050",
    "name": "대구광역시 북구",
    "level": "기초",
    "type": "자치구",
    "parent": "22"
  },
  "source": {
    "ordinance": {
      "name": "대구광역시 북구 행정기구 설치 조례",
      "mst": "2086919",
      "last_amended": "20260101",
      "url": "https://www.law.go.kr/DRF/lawService.do?OC=open&target=ordin&MST=2086919&type=HTML",
      "fetched_at": "2026-05-09"
    },
    "enforcement_rule": {
      "name": "대구광역시 북구 행정기구 설치 조례 시행규칙",
      "mst": "2101701",
      "last_amended": "20260101",
      "url": "https://www.law.go.kr/DRF/lawService.do?OC=open&target=ordin&MST=2101701&type=HTML",
      "fetched_at": "2026-05-09"
    },
    "staff_ordinance": {
      "name": "대구광역시 북구 지방공무원 정원 조례",
      "mst": "2086029",
      "last_amended": "20260101",
      "fetched_at": "2026-05-09"
    }
  },
  "totals": {
    "정원_총": 1174,
    "정원_근거조문": "대구광역시 북구 지방공무원 정원 조례 제2조",
    "정원_비고": ""
  },
  "structure": [
    {
      "id": "22050.감사실",
      "type": "실",
      "name": "감사실",
      "level": 1,
      "head_position": "감사실장",
      "head_grade": "",
      "정원": null,
      "근거조문": "조례 제4조",
      "분장사무_원문": "제4조 (감사실) 감사실장은 감사·조사 및 청렴윤리에 관한 사항을 분장한다.[제6조에서 이동 2024.6.5.]",
      "분장사무_항목": [],
      "키워드_태그": [
        "행정_기획"
      ],
      "children": []
    },
    {
      "id": "22050.정책기획국",
      "type": "국",
      "name": "정책기획국",
      "level": 1,
      "head_position": "정책기획국장",
      "head_grade": "5급",
      "정원": null,
      "근거조문": "조례 제5조",
      "분장사무_원문": "제5조(정책기획국)① 정책기획국에 기획예산과ㆍ정책소통과ㆍ혁신전략과ㆍ정보통신과를 둔다.<신설 2024.6.5.>② 정책기획국장은 다음 사항을 분장한다.<신설 2024.6.5.>1. 기획ㆍ예산 및 법무에 관한 사항2. 홍보소통ㆍ정책평가 및 빅데이터에 관한 사항3. 미래개발ㆍ혁신성장 및 인구청년정책에 관한 사항4. 정보행정ㆍ정보관리ㆍ정보통신 및 통합관제에 관한 사항",
      "분장사무_항목": [
        "기획ㆍ예산 및 법무에 관한 사항",
        "홍보소통ㆍ정책평가 및 빅데이터에 관한 사항",
        "미래개발ㆍ혁신성장 및 인구청년정책에 관한 사항",
        "정보행정ㆍ정보관리ㆍ정보통신 및 통합관제에 관한 사항"
      ],
      "키워드_태그": [
        "도시_건축",
        "행정_기획"
      ],
      "children": [
        {
          "id": "22050.정책기획국.기획예산과",
          "type": "과",
          "name": "기획예산과",
          "level": 2,
          "head_position": "기획예산과장",
          "head_grade": "",
          "정원": null,
          "근거조문": "시행규칙",
          "분장사무_원문": "",
          "분장사무_항목": [],
          "키워드_태그": [
            "행정_기획"
          ],
          "children": []
        },
        {
          "id": "22050.정책기획국.정책소통과",
          "type": "과",
          "name": "정책소통과",
          "level": 2,
          "head_position": "정책소통과장",
          "head_grade": "",
          "정원": null,
          "근거조문": "시행규칙",
          "분장사무_원문": "",
          "분장사무_항목": [],
          "키워드_태그": [],
          "children": []
        },
        {
          "id": "22050.정책기획국.혁신전략과",
          "type": "과",
          "name": "혁신전략과",
          "level": 2,
          "head_position": "혁신전략과장",
          "head_grade": "",
          "정원": null,
          "근거조문": "시행규칙",
          "분장사무_원문": "",
          "분장사무_항목": [],
          "키워드_태그": [],
          "children": []
        },
        {
          "id": "22050.정책기획국.정보통신과",
          "type": "과",
          "name": "정보통신과",
          "level": 2,
          "head_position": "정보통신과장",
          "head_grade": "",
          "정원": null,
          "근거조문": "시행규칙",
          "분장사무_원문": "",
          "분장사무_항목": [],
          "키워드_태그": [],
          "children": []
        }
      ]
    },
    {
      "id": "22050.복지환경국",
      "type": "국",
      "name": "복지환경국",
      "level": 1,
      "head_position": "복지환경국장",
      "head_grade": "5급",
      "정원": null,
      "근거조문": "조례 제8조",
      "분장사무_원문": "제8조(복지환경국) (제목개정 2021.05.31.)[제9조에서 이동 2024.6.5.]① 복지환경국에 복지정책과ㆍ생활보장과ㆍ희망복지과ㆍ여성아동과ㆍ환경관리과 및 자원순환과를 둔다.(개정 2021.05.31.)② 복지환경국장은 다음 사항을 분장한다.(개정 2021.05.31.)1. 복지정책ㆍ어르신정책ㆍ어르신시설ㆍ통합돌봄ㆍ복지자원 및 자활지원에 관한 사항(개정 2021.05.31, 2025.5.30, 2025.11.14.)2. 생활보장ㆍ통합관리 및 의료급여에 관한 사항(개정 2021.05.31.)3. 희망복지ㆍ통합조사 및 장애인복지에 관한 사항(신설 2021.05.31.)4. 여성아동ㆍ아동보호ㆍ보육지원 및 드림스타트에 관한 사항(개정.2021.05.31.)5. 환경관리·대기보전·수질보전 및 군소음보상에 관한 사항(개정 2021.12.30.)6. 청소행정·재활용·사업장관리 및 도시청결에 관한 사항",
      "분장사무_항목": [
        "복지정책ㆍ어르신정책ㆍ어르신시설ㆍ통합돌봄ㆍ복지자원 및 자활지원에 관한 사항(개정 2021.05.31, 2025.5.30, 2025.11.14.)",
        "생활보장ㆍ통합관리 및 의료급여에 관한 사항(개정 2021.05.31.)",
        "희망복지ㆍ통합조사 및 장애인복지에 관한 사항(신설 2021.05.31.)",
        "여성아동ㆍ아동보호ㆍ보육지원 및 드림스타트에 관한 사항(개정.2021.05.31.)",
        "환경관리·대기보전·수질보전 및 군소음보상에 관한 사항(개정 2021.12.30.)",
        "청소행정·재활용·사업장관리 및 도시청결에 관한 사항"
      ],
      "키워드_태그": [
        "환경",
        "복지",
        "도시_건축",
        "보건_위생"
      ],
      "children": [
        {
          "id": "22050.복지환경국.복지정책과",
          "type": "과",
          "name": "복지정책과",
          "level": 2,
          "head_position": "복지정책과장",
          "head_grade": "",
          "정원": null,
          "근거조문": "시행규칙",
          "분장사무_원문": "",
          "분장사무_항목": [],
          "키워드_태그": [
            "복지"
          ],
          "children": []
        },
        {
          "id": "22050.복지환경국.생활보장과",
          "type": "과",
          "name": "생활보장과",
          "level": 2,
          "head_position": "생활보장과장",
          "head_grade": "",
          "정원": null,
          "근거조문": "시행규칙",
          "분장사무_원문": "",
          "분장사무_항목": [],
          "키워드_태그": [],
          "children": []
        },
        {
          "id": "22050.복지환경국.희망복지과",
          "type": "과",
          "name": "희망복지과",
          "level": 2,
          "head_position": "희망복지과장",
          "head_grade": "",
          "정원": null,
          "근거조문": "시행규칙",
          "분장사무_원문": "",
          "분장사무_항목": [],
          "키워드_태그": [
            "복지"
          ],
          "children": []
        },
        {
          "id": "22050.복지환경국.여성아동과",
          "type": "과",
          "name": "여성아동과",
          "level": 2,
          "head_position": "여성아동과장",
          "head_grade": "",
          "정원": null,
          "근거조문": "시행규칙",
          "분장사무_원문": "",
          "분장사무_항목": [],
          "키워드_태그": [
            "복지"
          ],
          "children": []
        },
        {
          "id": "22050.복지환경국.환경관리과",
          "type": "과",
          "name": "환경관리과",
          "level": 2,
          "head_position": "환경관리과장",
          "head_grade": "",
          "정원": null,
          "근거조문": "시행규칙",
          "분장사무_원문": "",
          "분장사무_항목": [],
          "키워드_태그": [
            "환경"
          ],
          "children": []
        },
        {
          "id": "22050.복지환경국.자원순환과",
          "type": "과",
          "name": "자원순환과",
          "level": 2,
          "head_position": "자원순환과장",
          "head_grade": "",
          "정원": null,
          "근거조문": "시행규칙",
          "분장사무_원문": "",
          "분장사무_항목": [],
          "키워드_태그": [
            "환경"
          ],
          "children": []
        }
      ]
    }
  ],
  "validation": {
    "정원_합산_일치": null,
    "정원_총_조례기준": 1174,
    "분장사무_누락_부서": [],
    "비고": []
  }
}