{
  "region": {
    "code": "25040",
    "name": "대전광역시 유성구",
    "level": "기초",
    "type": "자치구",
    "parent": "25"
  },
  "source": {
    "ordinance": {
      "name": "대전광역시 유성구 행정기구 설치 조례",
      "mst": "2056565",
      "last_amended": "20250714",
      "url": "https://www.law.go.kr/DRF/lawService.do?OC=open&target=ordin&MST=2056565&type=HTML",
      "fetched_at": "2026-05-09"
    },
    "enforcement_rule": {
      "name": "대전광역시 유성구 행정기구 설치 조례 시행규칙",
      "mst": "2090445",
      "last_amended": "20251208",
      "url": "https://www.law.go.kr/DRF/lawService.do?OC=open&target=ordin&MST=2090445&type=HTML",
      "fetched_at": "2026-05-09"
    },
    "staff_ordinance": {
      "name": "대전광역시 유성구 지방공무원 정원 조례",
      "mst": "1942117",
      "last_amended": "20240701",
      "fetched_at": "2026-05-09"
    }
  },
  "totals": {
    "정원_총": 933,
    "정원_근거조문": "대전광역시 유성구 지방공무원 정원 조례 제2조",
    "정원_비고": ""
  },
  "structure": [
    {
      "id": "25040.감사실",
      "type": "실",
      "name": "감사실",
      "level": 1,
      "head_position": "감사실장",
      "head_grade": "",
      "정원": null,
      "근거조문": "조례 제6조의2",
      "분장사무_원문": "제6조의2(감사실) 감사실장은 다음 사항을 분장한다.<신설 2011.01.03><전부개정 2012.05.11>1. 감사 및 공무원비위 조사처리에 관한 사항2. 공직자 재산등록에 관한 사항",
      "분장사무_항목": [
        "감사 및 공무원비위 조사처리에 관한 사항",
        "공직자 재산등록에 관한 사항"
      ],
      "키워드_태그": [
        "행정_기획"
      ],
      "children": []
    },
    {
      "id": "25040.기획재정국",
      "type": "국",
      "name": "기획재정국",
      "level": 1,
      "head_position": "기획재정국장",
      "head_grade": "5급",
      "정원": null,
      "근거조문": "조례 제6조의5",
      "분장사무_원문": "제6조의5(기획재정국)① 기획재정국에 기획예산과, 홍보과, 세정과, 세원관리과를 둔다.② 기획재정국장은 다음 사항을 분장한다.1. 구 행정의 종합기획 조정2. 조직 및 정원관리3. 주요업무 시행계획 및 심사평가4. 지시사항 처리5. 예산의 편성운영6. 중기재정ㆍ중장기투자계획의 수립7. 조례ㆍ규칙 등 법제에 관한 사항8. 국제교류업무9. 통계조사의 종합계획 수립 및 조사, 보고10. 규제개혁 관련 업무추진 및 행정제도 개선에 관한 사항11. 데이터기반행정에 관한 사항12. 인구정책에 관한 사항13. 구정홍보에 관한 사항14. 공보에 관한 사항15. 편집실 운영16. 구 상징물 관련업무17. 전산업무18. 지방세 부과ㆍ징수19. 국세 위탁 징수20. 수입금 관리 및 자금배정[본조신설 2024.6.28.]",
      "분장사무_항목": [
        "구 행정의 종합기획 조정",
        "조직 및 정원관리",
        "주요업무 시행계획 및 심사평가",
        "지시사항 처리",
        "예산의 편성운영",
        "중기재정ㆍ중장기투자계획의 수립",
        "조례ㆍ규칙 등 법제에 관한 사항",
        "국제교류업무",
        "통계조사의 종합계획 수립 및 조사, 보고",
        "규제개혁 관련 업무추진 및 행정제도 개선에 관한 사항",
        "데이터기반행정에 관한 사항",
        "인구정책에 관한 사항",
        "구정홍보에 관한 사항",
        "공보에 관한 사항",
        "편집실 운영",
        "구 상징물 관련업무",
        "전산업무",
        "지방세 부과ㆍ징수",
        "국세 위탁 징수",
        "수입금 관리 및 자금배정[본조신설 2024.6.28.]"
      ],
      "키워드_태그": [
        "경제_산업",
        "행정_기획"
      ],
      "children": [
        {
          "id": "25040.기획재정국.기획예산과",
          "type": "과",
          "name": "기획예산과",
          "level": 2,
          "head_position": "기획예산과장",
          "head_grade": "",
          "정원": null,
          "근거조문": "시행규칙",
          "분장사무_원문": "제6조(기획예산과) 기획예산과장은 다음 사항을 분장한다.1. 구 행정의 종합기획 조정2. 주요업무 시행계획수립 및 심사평가3. 지시사항 총괄(대통령, 국무총리, 시장, 구청장)4. 사무위임 및 위임전결5. 직제 및 정원관리6. 예산편성운영 및 총괄7. 예산배정 계획수립 및 예산전용ㆍ이체승인8. 교부세 교부금 및 국ㆍ시비 보조금 운영9. 지방채, 기채, 채무부담행위 등에 관한 신청과 예산집행10. 중기재정계획 및 투자계획수립11. 규제개혁종합추진12. 자체 혁신업무 총괄13. 조례ㆍ규칙ㆍ훈령의 제ㆍ개정 및 폐지에 관한 사항14. 소송사무의 종합 및 조정 관리15. 국제교류업무의 종합계획 조정16. 외국도시와 자매결연 및 교류에 관한 사항17. 자치단체와의 협력에 관한 사항18. 통계에 관한 사항19. 규제개혁 관련 정부정책 추진20. 기업 등 지역현장 규제애로 발굴 및 제도개선21. 중앙부처 법령개선 건의과제 발굴22. 행정제도 개선에 관한 사항23. 구 의회 협력에 관한 사항24. 중장기 정책 계획 수립 및 발굴25. 데이터기반행정에 관한 사항26. 공공데이터 제공 및 이용 활성화에 관한 사항27. 데이터 분석 인프라 구축 및 관리28. 데이터 활용역량 강화에 관한 사항29. 데이터 거버넌스 구축 및 유관기관 협력사업 발굴30. 인구정책 계획 수립 및 정책 발굴",
          "분장사무_항목": [
            "구 행정의 종합기획 조정",
            "주요업무 시행계획수립 및 심사평가",
            "지시사항 총괄(대통령, 국무총리, 시장, 구청장)",
            "사무위임 및 위임전결",
            "직제 및 정원관리",
            "예산편성운영 및 총괄",
            "예산배정 계획수립 및 예산전용ㆍ이체승인",
            "교부세 교부금 및 국ㆍ시비 보조금 운영",
            "지방채, 기채, 채무부담행위 등에 관한 신청과 예산집행",
            "중기재정계획 및 투자계획수립",
            "규제개혁종합추진",
            "자체 혁신업무 총괄",
            "조례ㆍ규칙ㆍ훈령의 제ㆍ개정 및 폐지에 관한 사항",
            "소송사무의 종합 및 조정 관리",
            "국제교류업무의 종합계획 조정",
            "외국도시와 자매결연 및 교류에 관한 사항",
            "자치단체와의 협력에 관한 사항",
            "통계에 관한 사항",
            "규제개혁 관련 정부정책 추진",
            "기업 등 지역현장 규제애로 발굴 및 제도개선",
            "중앙부처 법령개선 건의과제 발굴",
            "행정제도 개선에 관한 사항",
            "구 의회 협력에 관한 사항",
            "중장기 정책 계획 수립 및 발굴",
            "데이터기반행정에 관한 사항",
            "공공데이터 제공 및 이용 활성화에 관한 사항",
            "데이터 분석 인프라 구축 및 관리",
            "데이터 활용역량 강화에 관한 사항",
            "데이터 거버넌스 구축 및 유관기관 협력사업 발굴",
            "인구정책 계획 수립 및 정책 발굴"
          ],
          "키워드_태그": [
            "도시_건축",
            "행정_기획"
          ],
          "children": []
        },
        {
          "id": "25040.기획재정국.홍보과",
          "type": "과",
          "name": "홍보과",
          "level": 2,
          "head_position": "홍보과장",
          "head_grade": "",
          "정원": null,
          "근거조문": "시행규칙",
          "분장사무_원문": "제7조(홍보과) 홍보과장은 다음 사항을 분장한다.1. 국ㆍ시ㆍ구정 홍보2. 편집실 운영3. 뉴미디어 홍보업무 추진4. 구청장 외부특강 및 인터뷰자료 작성5. 구정홍보물 관리6. 구 상징물(구마크, 구정구호 등) 관리7. 구 홈페이지 컨텐츠 개발 및 운영에 관한 사항8. 각종 행정정보화 시책사업 발굴 및 추진9. 지역정보화촉진 계획 수립 및 시행10. 지역정보화사업 발굴 및 시책화 추진11. 정보화 시스템 구축 및 유지관리12. 정보시스템 표준화 및 확대 보급13. 각종 웹시스템 구축 및 운영14. 지역주민과 공무원에 대한 정보화 교육 추진15. 전자정부통합망 구축 및 운영관리16. 개인정보 보호 및 정보보호시스템 운영17. 각종 소프트웨어 보급 및 관리운영18. 행정정보 공동이용에 관한 사항19. 전자정부원격지원에 관한 사항20. 전자문서시스템 운영에 관한 사항21. 공통기반(새올, 인사, 지방세, 이호조, 세움터 등)시스템 운영에 관한 사항22. 시군구행정정보시스템 운영에 관한 사항",
          "분장사무_항목": [
            "국ㆍ시ㆍ구정 홍보",
            "편집실 운영",
            "뉴미디어 홍보업무 추진",
            "구청장 외부특강 및 인터뷰자료 작성",
            "구정홍보물 관리",
            "구 상징물(구마크, 구정구호 등) 관리",
            "구 홈페이지 컨텐츠 개발 및 운영에 관한 사항",
            "각종 행정정보화 시책사업 발굴 및 추진",
            "지역정보화촉진 계획 수립 및 시행",
            "지역정보화사업 발굴 및 시책화 추진",
            "정보화 시스템 구축 및 유지관리",
            "정보시스템 표준화 및 확대 보급",
            "각종 웹시스템 구축 및 운영",
            "지역주민과 공무원에 대한 정보화 교육 추진",
            "전자정부통합망 구축 및 운영관리",
            "개인정보 보호 및 정보보호시스템 운영",
            "각종 소프트웨어 보급 및 관리운영",
            "행정정보 공동이용에 관한 사항",
            "전자정부원격지원에 관한 사항",
            "전자문서시스템 운영에 관한 사항",
            "공통기반(새올, 인사, 지방세, 이호조, 세움터 등)시스템 운영에 관한 사항",
            "시군구행정정보시스템 운영에 관한 사항"
          ],
          "키워드_태그": [
            "도시_건축",
            "행정_기획",
            "문화_교육"
          ],
          "children": []
        },
        {
          "id": "25040.기획재정국.세정과",
          "type": "과",
          "name": "세정과",
          "level": 2,
          "head_position": "세정과장",
          "head_grade": "",
          "정원": null,
          "근거조문": "시행규칙",
          "분장사무_원문": "제8조(세정과) 세정과장은 다음 사항을 분장한다.1. 세무행정의 종합기획2. 지방세 부과 징수3. 지방세 이의신청 및 심사청구의 처리4. 부과관계 공부열람5. 제증명의 발급사항6. 지방세 납기한 및 징수유예7. 지방세 전산화 사업추진 총괄8. 지방세심의위원회 총괄9. 지방세지출예산제도 총괄",
          "분장사무_항목": [
            "세무행정의 종합기획",
            "지방세 부과 징수",
            "지방세 이의신청 및 심사청구의 처리",
            "부과관계 공부열람",
            "제증명의 발급사항",
            "지방세 납기한 및 징수유예",
            "지방세 전산화 사업추진 총괄",
            "지방세심의위원회 총괄",
            "지방세지출예산제도 총괄"
          ],
          "키워드_태그": [
            "행정_기획"
          ],
          "children": []
        },
        {
          "id": "25040.기획재정국.세원관리과",
          "type": "과",
          "name": "세원관리과",
          "level": 2,
          "head_position": "세원관리과장",
          "head_grade": "",
          "정원": null,
          "근거조문": "시행규칙",
          "분장사무_원문": "제9조(세원관리과) 세원관리과장은 다음 사항을 분장한다.1. 지방세 부과 징수2. 지방세 이의신청 및 심사청구의 처리3. 건물 및 기타물건의 과세표준액에 관한 사항4. 세원발굴 및 세무조사5. 세입의 결산(일일결산, 월ㆍ기보)6. 세입월계표 및 영수필통지서 관리7. 지방세 납기한 및 징수유예8. 자금수급 및 관리9. 구금고 운영 및 수납기관 지도감독10. 과오납금 환부11. 지방세 체납액 징수 및 체납처분12. 지방세 결손처분13. 지방세 가산금 조정 및 독촉14. 일반회계 세외수입 징수15. 일반회계 세외수입 체납액 징수 및 체납처분16. 일반회계 세외수입 결손처분17. 개별주택가격 조사 산정에 관한 계획 수립18. 건물현황 및 주택특성조사 시가산정에 관한 사항19. 개별주택가격 시가의 결정ㆍ공시 및 개별 통지20. 개별주택가격에 대한 시가 열람 및 의견ㆍ이의신청 접수21. 부동산가격공시위원회 운영에 관한 사항",
          "분장사무_항목": [
            "지방세 부과 징수",
            "지방세 이의신청 및 심사청구의 처리",
            "건물 및 기타물건의 과세표준액에 관한 사항",
            "세원발굴 및 세무조사",
            "세입의 결산(일일결산, 월ㆍ기보)",
            "세입월계표 및 영수필통지서 관리",
            "지방세 납기한 및 징수유예",
            "자금수급 및 관리",
            "구금고 운영 및 수납기관 지도감독",
            "과오납금 환부",
            "지방세 체납액 징수 및 체납처분",
            "지방세 결손처분",
            "지방세 가산금 조정 및 독촉",
            "일반회계 세외수입 징수",
            "일반회계 세외수입 체납액 징수 및 체납처분",
            "일반회계 세외수입 결손처분",
            "개별주택가격 조사 산정에 관한 계획 수립",
            "건물현황 및 주택특성조사 시가산정에 관한 사항",
            "개별주택가격 시가의 결정ㆍ공시 및 개별 통지",
            "개별주택가격에 대한 시가 열람 및 의견ㆍ이의신청 접수",
            "부동산가격공시위원회 운영에 관한 사항"
          ],
          "키워드_태그": [
            "도시_건축"
          ],
          "children": []
        }
      ]
    },
    {
      "id": "25040.자치행정국",
      "type": "국",
      "name": "자치행정국",
      "level": 1,
      "head_position": "자치행정국장",
      "head_grade": "5급",
      "정원": null,
      "근거조문": "조례 제7조",
      "분장사무_원문": "제7조(자치행정국)① 자치행정국에 운영지원과, 마을자치과, 회계과, 민원여권과, 토지정보과를 둔다.② 자치행정국장은 다음 사항을 분장한다.1. 공무원의 인사, 교육훈련2. 보안업무3. 공무원단체 지원ㆍ협조 및 비정규직 업무4. 선거 및 행정구역 조정5. 새마을 운동6. 반상회 및 동 행정 지도7. 주민자치센터 운영8. 마을공동체에 관한 사항9. 공사도급, 세출예산의 정리결산10. 세입세출외 현금 및 유가증권의 출납보관11. 복식부기 회계업무 처리12. 복식부기 회계에 의한 자산ㆍ부채의 관리13. 복식부기 회계결산 및 보고 (기초 재정상태 보고서 작성 등)14. 영선업무에 관한 사항15. 방송ㆍ통신ㆍ음향시설에 관한 업무16. 방범용 CCTV에 관한 업무17. 민원행정 및 주민등록 총괄18. 여권업무19. 가족관계등록에 관한 사항20. 공인사용, 기록물 관리 및 정보공개에 관한 사항21. 공유재산 관리22. 토지관리 업무의 종합기획23. 지적공부의 보존관리24. 지적측량에 관한 사항25. 도로명 및 건물번호 부여사업[전문개정 2024.6.28.]",
      "분장사무_항목": [
        "공무원의 인사, 교육훈련",
        "보안업무",
        "공무원단체 지원ㆍ협조 및 비정규직 업무",
        "선거 및 행정구역 조정",
        "새마을 운동",
        "반상회 및 동 행정 지도",
        "주민자치센터 운영",
        "마을공동체에 관한 사항",
        "공사도급, 세출예산의 정리결산",
        "세입세출외 현금 및 유가증권의 출납보관",
        "복식부기 회계업무 처리",
        "복식부기 회계에 의한 자산ㆍ부채의 관리",
        "복식부기 회계결산 및 보고 (기초 재정상태 보고서 작성 등)",
        "영선업무에 관한 사항",
        "방송ㆍ통신ㆍ음향시설에 관한 업무",
        "방범용 CCTV에 관한 업무",
        "민원행정 및 주민등록 총괄",
        "여권업무",
        "가족관계등록에 관한 사항",
        "공인사용, 기록물 관리 및 정보공개에 관한 사항",
        "공유재산 관리",
        "토지관리 업무의 종합기획",
        "지적공부의 보존관리",
        "지적측량에 관한 사항",
        "도로명 및 건물번호 부여사업[전문개정 2024.6.28.]"
      ],
      "키워드_태그": [
        "교통",
        "행정_기획",
        "문화_교육"
      ],
      "children": [
        {
          "id": "25040.자치행정국.운영지원과",
          "type": "과",
          "name": "운영지원과",
          "level": 2,
          "head_position": "운영지원과장",
          "head_grade": "",
          "정원": null,
          "근거조문": "시행규칙",
          "분장사무_원문": "제11조(운영지원과) 운영지원과장은 다음 사항을 분장한다.1. 보안업무의 총괄2. 의전에 관한 사항3. 청사방호4. 직장민방위대 운영5. 공인 관리(신조, 개각)에 관한 사항6. 공무원 복무에 관한 사항7. 공무원 임용에 관한 사항8. 공무원 평정(경력ㆍ근무성적 및 서열명부 작성)9. 공무원 교육훈련 및 상훈10. 공무원 노동조합에 관한 사항11. 단체교섭 및 단체ㆍ임금협약 체결에 관한 사항(환경노동조합 제외)12. 기간제 근로자 관리에 관한 사항13. 공무국외여행 허가에 관한 업무14. 국경일에 관한 사항15. 바르게살기협의회 등 단체 관리16. 평화통일정책자문회의 관련 업무17. 유성커뮤니티센터 관리에 관한 사항18. 공무직 근로자 관리에 관한 사항(환경관리요원 제외)19. 공무직 노동조합에 관한 사항(환경노동조합 제외)20. 직장어린이집 운영에 관한 사항21. 맞춤형 복지에 관한 사항",
          "분장사무_항목": [
            "보안업무의 총괄",
            "의전에 관한 사항",
            "청사방호",
            "직장민방위대 운영",
            "공인 관리(신조, 개각)에 관한 사항",
            "공무원 복무에 관한 사항",
            "공무원 임용에 관한 사항",
            "공무원 평정(경력ㆍ근무성적 및 서열명부 작성)",
            "공무원 교육훈련 및 상훈",
            "공무원 노동조합에 관한 사항",
            "단체교섭 및 단체ㆍ임금협약 체결에 관한 사항(환경노동조합 제외)",
            "기간제 근로자 관리에 관한 사항",
            "공무국외여행 허가에 관한 업무",
            "국경일에 관한 사항",
            "바르게살기협의회 등 단체 관리",
            "평화통일정책자문회의 관련 업무",
            "유성커뮤니티센터 관리에 관한 사항",
            "공무직 근로자 관리에 관한 사항(환경관리요원 제외)",
            "공무직 노동조합에 관한 사항(환경노동조합 제외)",
            "직장어린이집 운영에 관한 사항",
            "맞춤형 복지에 관한 사항"
          ],
          "키워드_태그": [
            "환경",
            "복지",
            "재난_안전",
            "문화_교육"
          ],
          "children": []
        },
        {
          "id": "25040.자치행정국.마을자치과",
          "type": "과",
          "name": "마을자치과",
          "level": 2,
          "head_position": "마을자치과장",
          "head_grade": "",
          "정원": null,
          "근거조문": "시행규칙",
          "분장사무_원문": "제12조(마을자치과) 마을자치과장은 다음 사항을 분장한다.1. 선거 및 국민ㆍ주민투표에 관한 사항2. 동 행정 지도ㆍ감독3. 행정구역 통ㆍ반 설치 운영4. 새마을에 관한 사항5. 새마을 시설물 관리6. 새마을금고에 관한 사항(설립인가 등)7. 장관(행정안전부)지시사항 처리8. 행정사 지도ㆍ감독9. 북한 이탈주민 거주지 보호에 관한 사항10. 주민자치센터 운영에 관한 사항11. 행정서비스헌장에 관한 사항12. 적십자 업무에 관한 사항13. 희망마을 만들기 사업14. 기부금 심사위원회 운영 등에 관한 사항15. 주민등록 및 인감에 관한 사항16. 주민등록 전산정보자료의 이용 및 활용에 관한 승인17. 자원봉사센터 관리 및 지원18. 납북피해신고 사실조사에 관한 사항19. 일제강점하 강제동원 피해자 신고관련 업무20. 주민참여예산제에 관한 사항21. 자율방범대 지원에 관한 사항22. 무인택배 보관함 설치ㆍ운영에 관한 사항23. 자치분권 전반에 관한 사항24. 마을공동체 사업기획 및 전반에 관한 사항25. 균형발전 업무 총괄(지방이양사무 포함)26. 고향사랑기부제에 관한 사항",
          "분장사무_항목": [
            "선거 및 국민ㆍ주민투표에 관한 사항",
            "동 행정 지도ㆍ감독",
            "행정구역 통ㆍ반 설치 운영",
            "새마을에 관한 사항",
            "새마을 시설물 관리",
            "새마을금고에 관한 사항(설립인가 등)",
            "장관(행정안전부)지시사항 처리",
            "행정사 지도ㆍ감독",
            "북한 이탈주민 거주지 보호에 관한 사항",
            "주민자치센터 운영에 관한 사항",
            "행정서비스헌장에 관한 사항",
            "적십자 업무에 관한 사항",
            "희망마을 만들기 사업",
            "기부금 심사위원회 운영 등에 관한 사항",
            "주민등록 및 인감에 관한 사항",
            "주민등록 전산정보자료의 이용 및 활용에 관한 승인",
            "자원봉사센터 관리 및 지원",
            "납북피해신고 사실조사에 관한 사항",
            "일제강점하 강제동원 피해자 신고관련 업무",
            "주민참여예산제에 관한 사항",
            "자율방범대 지원에 관한 사항",
            "무인택배 보관함 설치ㆍ운영에 관한 사항",
            "자치분권 전반에 관한 사항",
            "마을공동체 사업기획 및 전반에 관한 사항",
            "균형발전 업무 총괄(지방이양사무 포함)",
            "고향사랑기부제에 관한 사항"
          ],
          "키워드_태그": [
            "재난_안전",
            "행정_기획"
          ],
          "children": []
        },
        {
          "id": "25040.자치행정국.회계과",
          "type": "과",
          "name": "회계과",
          "level": 2,
          "head_position": "회계과장",
          "head_grade": "",
          "정원": null,
          "근거조문": "시행규칙",
          "분장사무_원문": "제13조(회계과) 회계과장은 다음 사항을 분장한다.1. 예산의 집행 및 자금교부2. 공사 제조ㆍ용역 및 물품구매 조달3. 시설공사의 하자관리4. 세출예산의 정리 및 회계결산5. 근로소득 원천징수 및 납입6. 차량 및 장비의 구입ㆍ수선관리7. 복식부기 회계제도 도입 및 운영에 관한 사항8. 새마을회관 등 공공시설물 신축 및 증축 시 예정금액 1억원 이상인 사업의 건축 기본설계 단계부터 준공까지 모든 업무 추진과 예산집행(다만, 사업기본계획 수립, 예산확보, 부지 확보, 공사 관련 행사 및 준공된 시설물의 관리는 주관부서에서 한다)9. 구 청사관리 등 영선업무에 관한 사항10. 청사청소 및 방화관리11. 통신보안업무에 관한 사항12. 단문메시지 및 팩스서버시스템 운영관리13. 본청 및 산하기관의 통신시설 유지ㆍ관리14. 정보통신공사 사용전검사 업무15. 공공건축물 정보통신 시설공사 관련 설계용역, 공사감독 등16. 행정방송ㆍ음향시설의 유지관리17. CCTV 통합운영ㆍ관리에 관한 사항",
          "분장사무_항목": [
            "예산의 집행 및 자금교부",
            "공사 제조ㆍ용역 및 물품구매 조달",
            "시설공사의 하자관리",
            "세출예산의 정리 및 회계결산",
            "근로소득 원천징수 및 납입",
            "차량 및 장비의 구입ㆍ수선관리",
            "복식부기 회계제도 도입 및 운영에 관한 사항",
            "새마을회관 등 공공시설물 신축 및 증축 시 예정금액 1억원 이상인 사업의 건축 기본설계 단계부터 준공까지 모든 업무 추진과 예산집행(다만, 사업기본계획 수립, 예산확보, 부지 확보, 공사 관련 행사 및 준공된 시설물의 관리는 주관부서에서 한다)",
            "구 청사관리 등 영선업무에 관한 사항",
            "청사청소 및 방화관리",
            "통신보안업무에 관한 사항",
            "단문메시지 및 팩스서버시스템 운영관리",
            "본청 및 산하기관의 통신시설 유지ㆍ관리",
            "정보통신공사 사용전검사 업무",
            "공공건축물 정보통신 시설공사 관련 설계용역, 공사감독 등",
            "행정방송ㆍ음향시설의 유지관리",
            "CCTV 통합운영ㆍ관리에 관한 사항"
          ],
          "키워드_태그": [
            "도시_건축",
            "행정_기획"
          ],
          "children": []
        },
        {
          "id": "25040.자치행정국.민원여권과",
          "type": "과",
          "name": "민원여권과",
          "level": 2,
          "head_position": "민원여권과장",
          "head_grade": "",
          "정원": null,
          "근거조문": "시행규칙",
          "분장사무_원문": "제14조(민원여권과) 민원여권과장은 다음 사항을 분장한다.1. 민원제도개선에 관한 사항2. 민원사무심사3. 유기한 민원접수 및 증명민원(주민등록 등ㆍ초본, 인감증명, 제적 등ㆍ초본) 발급4. 민원사무 관련 지도ㆍ감독5. 무인 민원발급 창구 운영6. 외국인 등록 및 일반 업무7. 행정정보 공동이용(G4C)에 관한 사무8. 공문서의 수발 및 배부9. 공인사용 및 관리10. 기록관시스템 운영관리11. 기록관 및 행정자료실 운영12. 기록물의 수집ㆍ보존 및 활용13. 기록물에 관한 정보공개 접수 및 평가, 교육14. 가족관계등록에 관한 사무15. 수형인명부 및 파산자의 기록관리16. 신원조회17. 여권에 관한 사항18. 고객만족(CS)업무 추진",
          "분장사무_항목": [
            "민원제도개선에 관한 사항",
            "민원사무심사",
            "유기한 민원접수 및 증명민원(주민등록 등ㆍ초본, 인감증명, 제적 등ㆍ초본) 발급",
            "민원사무 관련 지도ㆍ감독",
            "무인 민원발급 창구 운영",
            "외국인 등록 및 일반 업무",
            "행정정보 공동이용(G4C)에 관한 사무",
            "공문서의 수발 및 배부",
            "공인사용 및 관리",
            "기록관시스템 운영관리",
            "기록관 및 행정자료실 운영",
            "기록물의 수집ㆍ보존 및 활용",
            "기록물에 관한 정보공개 접수 및 평가, 교육",
            "가족관계등록에 관한 사무",
            "수형인명부 및 파산자의 기록관리",
            "신원조회",
            "여권에 관한 사항",
            "고객만족(CS)업무 추진"
          ],
          "키워드_태그": [
            "행정_기획",
            "문화_교육"
          ],
          "children": []
        },
        {
          "id": "25040.자치행정국.토지정보과",
          "type": "과",
          "name": "토지정보과",
          "level": 2,
          "head_position": "토지정보과장",
          "head_grade": "",
          "정원": null,
          "근거조문": "시행규칙",
          "분장사무_원문": "제15조(토지정보과) 토지정보과장은 다음 사항을 분장한다.1. 토지거래계약 허가 및 사후 이행실태조사2. 부동산 매매계약서 검인3. 부동산 등기신청해태 과태료 부과ㆍ징수4.「부동산 거래신고 등에 관한 법률」 위반 과태료 부과ㆍ징수5. 개별공시지가에 관한 사항6. 부동산중개업에 관한 사항7. 지적민원 처리8. 지적공부 등본교부 및 열람9. 토지소유권 정리10. 토지표시변경 등기촉탁 및 미등기토지 주소등록11. 토지이용계획 확인서발급12. 토지소유사실확인서 발급13. 부동산 실권리자 명의등기에 관한 사항14. 지적공부 보존관리 및 지적도면 전산화시스템 운영15. 지적측량 성과검사 및 측량기준점 관리16. 지적 재조사사업 추진17. 지적측량 대행법인의 지도ㆍ감독18. 지적복구 및 토지분할 허가에 관한 사항19. 국가소송수행(지적, 국유재산분야)20. 등록사항 정정대상 토지조사 정리21.「공유토지분할에 관한 특례법」에 관한 사항22. 축척변경 및 지적불부합지 정리23. 도로명 및 건물번호부여 사업 추진24. 택지초과소유부담금 사후관리25. 개발부담금 부과ㆍ징수26. 공유재산 관리 및 수립27. 시ㆍ구유재산(일반재산)의 대부 및 재산관리28. 부동산가격공시위원회 운영29. 외국인토지취득신고 및 위반과태료 부과ㆍ징수30. 토지이동 정리31. 지적통계 및 보고32. 법인 아닌 사단재단등록번호부여 및 발급33. 지적측량장비 운영 및 관리34. 국토정보센터의 운영 및 관리35. 부동산거래신고에 관한 사항36. 한국토지정보시스템 운영 및 유지관리37. 공유재산 취득 및 처분에 관한 사항38. 도시개발사업 시행신고 및 완료신고 처리39. 지적위성측량 시험운영 및 도입 추진40. 공유재산 공제업무에 관한 사항41. 지명위원회 운영에 관한 사항",
          "분장사무_항목": [
            "토지거래계약 허가 및 사후 이행실태조사",
            "부동산 매매계약서 검인",
            "부동산 등기신청해태 과태료 부과ㆍ징수4.「부동산 거래신고 등에 관한 법률」 위반 과태료 부과ㆍ징수",
            "개별공시지가에 관한 사항",
            "부동산중개업에 관한 사항",
            "지적민원 처리",
            "지적공부 등본교부 및 열람",
            "토지소유권 정리",
            "토지표시변경 등기촉탁 및 미등기토지 주소등록",
            "토지이용계획 확인서발급",
            "토지소유사실확인서 발급",
            "부동산 실권리자 명의등기에 관한 사항",
            "지적공부 보존관리 및 지적도면 전산화시스템 운영",
            "지적측량 성과검사 및 측량기준점 관리",
            "지적 재조사사업 추진",
            "지적측량 대행법인의 지도ㆍ감독",
            "지적복구 및 토지분할 허가에 관한 사항",
            "국가소송수행(지적, 국유재산분야)",
            "등록사항 정정대상 토지조사 정리21.「공유토지분할에 관한 특례법」에 관한 사항",
            "축척변경 및 지적불부합지 정리",
            "도로명 및 건물번호부여 사업 추진",
            "택지초과소유부담금 사후관리",
            "개발부담금 부과ㆍ징수",
            "공유재산 관리 및 수립",
            "시ㆍ구유재산(일반재산)의 대부 및 재산관리",
            "부동산가격공시위원회 운영",
            "외국인토지취득신고 및 위반과태료 부과ㆍ징수",
            "토지이동 정리",
            "지적통계 및 보고",
            "법인 아닌 사단재단등록번호부여 및 발급",
            "지적측량장비 운영 및 관리",
            "국토정보센터의 운영 및 관리",
            "부동산거래신고에 관한 사항",
            "한국토지정보시스템 운영 및 유지관리",
            "공유재산 취득 및 처분에 관한 사항",
            "도시개발사업 시행신고 및 완료신고 처리",
            "지적위성측량 시험운영 및 도입 추진",
            "공유재산 공제업무에 관한 사항",
            "지명위원회 운영에 관한 사항"
          ],
          "키워드_태그": [
            "교통",
            "도시_건축"
          ],
          "children": []
        }
      ]
    },
    {
      "id": "25040.경제문화국",
      "type": "국",
      "name": "경제문화국",
      "level": 1,
      "head_position": "경제문화국장",
      "head_grade": "5급",
      "정원": null,
      "근거조문": "조례 제7조의2",
      "분장사무_원문": "제7조의2(경제문화국)① 경제문화국에 일자리정책과, 문화관광체육과, 교육과학과, 지역산업과를 둔다.② 경제문화국장은 다음 사항을 분장한다.1. 일자리 관련 업무(장애인 및 노인일자리 제외)2. 지역단위 경제발전계획의 수립3. 저축업무 및 금융지원4. 상ㆍ공업 진흥계획수립과 산업단지 조성에 관한 사항5. 제조담배 소매업의 등록 및 관리6. 자치단체와 기업간의 협력에 관한 사항7. 노동조합업무8. 사회적 경제에 관한 사항9. 청년 및 1인가구 정책에 관한 사항10. 지방문화예술의 진흥11. 국가유산 보호관리12. 관광발전 및 진흥에 관한 사항13. 체육진흥에 관한 사항14. 체육시설 위탁 및 지도ㆍ점검에 관한 사항15. 온천업무에 관한 사항16. 학교 교육 및 협력에 관한 사항17. 장학재단 관련 업무18. 청소년 관련 업무19. 대덕연구개발특구와의 협력에 관한 사항20. 과학기술 관련 업무21. 행정업무 디지털 혁신에 관한 사항22. 농ㆍ축산업의 진흥23. 친환경 급식 및 로컬푸드에 관한 사항[전문개정 2024.6.28.]",
      "분장사무_항목": [
        "일자리 관련 업무(장애인 및 노인일자리 제외)",
        "지역단위 경제발전계획의 수립",
        "저축업무 및 금융지원",
        "상ㆍ공업 진흥계획수립과 산업단지 조성에 관한 사항",
        "제조담배 소매업의 등록 및 관리",
        "자치단체와 기업간의 협력에 관한 사항",
        "노동조합업무",
        "사회적 경제에 관한 사항",
        "청년 및 1인가구 정책에 관한 사항",
        "지방문화예술의 진흥",
        "국가유산 보호관리",
        "관광발전 및 진흥에 관한 사항",
        "체육진흥에 관한 사항",
        "체육시설 위탁 및 지도ㆍ점검에 관한 사항",
        "온천업무에 관한 사항",
        "학교 교육 및 협력에 관한 사항",
        "장학재단 관련 업무",
        "청소년 관련 업무",
        "대덕연구개발특구와의 협력에 관한 사항",
        "과학기술 관련 업무",
        "행정업무 디지털 혁신에 관한 사항",
        "농ㆍ축산업의 진흥",
        "친환경 급식 및 로컬푸드에 관한 사항[전문개정 2024.6.28.]"
      ],
      "키워드_태그": [
        "환경",
        "복지",
        "도시_건축",
        "경제_산업",
        "문화_교육"
      ],
      "children": [
        {
          "id": "25040.경제문화국.일자리정책과",
          "type": "과",
          "name": "일자리정책과",
          "level": 2,
          "head_position": "일자리정책과장",
          "head_grade": "",
          "정원": null,
          "근거조문": "시행규칙",
          "분장사무_원문": "제17조(일자리정책과) 일자리정책과장은 다음 사항을 분장한다.1. 정부지원 일자리업무 추진(공공근로, 지역공동체 일자리 등)2. 일자리 창출(장애인 및 노인일자리 제외)3. 일자리 공시제도4. 생활임금제 업무5. 일자리지원센터 운영6. 직업소개소 등록 및 관리7. 지역경제의 발전에 관한 종합기획 조정8. 지역물가안정 관리에 관한 사항9. 상점가 및 소상공인 지원에 관한 사항10. 전통시장 육성 및 지원11. 중소기업 지원ㆍ육성 및 유치에 관한 사항12. 공장등록에 관한 사항13. 소비자 보호에 관한 사항14. 담배소매업의 지정15. 통신ㆍ방문ㆍ전화권유 판매업에 관한 사항16. 노동조합 설립에 관한 사항17. 자치단체와 기업과의 협력 사항18. 계량기 및 시장개설허가 등에 관한 사항19. 부정경쟁방지 업무에 관한 사항20. 사회적경제에 관한 사항21. 마을기업에 관한 사항22. 협동조합 추진에 관한 사항23. 창업혁신생태계 조성에 관한 사항24. 청년정책 및 지원에 관한 사항25. 1인가구 정책 발굴26. 대학 협력사업 추진",
          "분장사무_항목": [
            "정부지원 일자리업무 추진(공공근로, 지역공동체 일자리 등)",
            "일자리 창출(장애인 및 노인일자리 제외)",
            "일자리 공시제도",
            "생활임금제 업무",
            "일자리지원센터 운영",
            "직업소개소 등록 및 관리",
            "지역경제의 발전에 관한 종합기획 조정",
            "지역물가안정 관리에 관한 사항",
            "상점가 및 소상공인 지원에 관한 사항",
            "전통시장 육성 및 지원",
            "중소기업 지원ㆍ육성 및 유치에 관한 사항",
            "공장등록에 관한 사항",
            "소비자 보호에 관한 사항",
            "담배소매업의 지정",
            "통신ㆍ방문ㆍ전화권유 판매업에 관한 사항",
            "노동조합 설립에 관한 사항",
            "자치단체와 기업과의 협력 사항",
            "계량기 및 시장개설허가 등에 관한 사항",
            "부정경쟁방지 업무에 관한 사항",
            "사회적경제에 관한 사항",
            "마을기업에 관한 사항",
            "협동조합 추진에 관한 사항",
            "창업혁신생태계 조성에 관한 사항",
            "청년정책 및 지원에 관한 사항",
            "1인가구 정책 발굴",
            "대학 협력사업 추진"
          ],
          "키워드_태그": [
            "녹지_생태",
            "복지",
            "경제_산업",
            "행정_기획"
          ],
          "children": []
        },
        {
          "id": "25040.경제문화국.문화관광체육과",
          "type": "과",
          "name": "문화관광체육과",
          "level": 2,
          "head_position": "문화관광체육과장",
          "head_grade": "",
          "정원": null,
          "근거조문": "시행규칙",
          "분장사무_원문": "제18조(문화관광체육과) 문화관광체육과장은 다음 사항을 분장한다.1. 지방문화예술진흥계획 수립2. 출판사, 인쇄소, 음반ㆍ비디오물 및 게임물의 등록 등에 관한 사항3. 공연장 설치허가 및 지도4. 종교단체지도5. 문화재 보호 관리6. 광고영화 검열 및 유선방송에 관한 사항7. 관광행정의 종합계획 조정8. 관광홍보 및 안내9. 관광자원의 조사ㆍ개발10. 체육시설업의 등록신고 및 지도ㆍ감독 등11. 공공체육시설의 운영관리12. 학교체육시설 개방관련 업무13. 건전생활에 관한 사항14. 체육진흥 시책추진15. 각종 레포츠시설 관리16. 국외여행업 및 국내여행업에 관한 사항17. 관광편의시설업(관광유흥음식점업) 지정에 관한 사항18. 직장운동경기부 지도ㆍ감독 및 관리19. 유원시설업의 허가 등에 관한 사항20. 온천자원의 보호 및 효율적인 개발관리21. 온천수 공동급수 및 사용료의 징수22. 온천지구 내 각종 금지행위 지도단속23. 온천수 급수시설 설치 및 유지관리24. 그 밖에 온천개발 및 공공시설 유지관리에 관한 사항",
          "분장사무_항목": [
            "지방문화예술진흥계획 수립",
            "출판사, 인쇄소, 음반ㆍ비디오물 및 게임물의 등록 등에 관한 사항",
            "공연장 설치허가 및 지도",
            "종교단체지도",
            "문화재 보호 관리",
            "광고영화 검열 및 유선방송에 관한 사항",
            "관광행정의 종합계획 조정",
            "관광홍보 및 안내",
            "관광자원의 조사ㆍ개발",
            "체육시설업의 등록신고 및 지도ㆍ감독 등",
            "공공체육시설의 운영관리",
            "학교체육시설 개방관련 업무",
            "건전생활에 관한 사항",
            "체육진흥 시책추진",
            "각종 레포츠시설 관리",
            "국외여행업 및 국내여행업에 관한 사항",
            "관광편의시설업(관광유흥음식점업) 지정에 관한 사항",
            "직장운동경기부 지도ㆍ감독 및 관리",
            "유원시설업의 허가 등에 관한 사항",
            "온천자원의 보호 및 효율적인 개발관리",
            "온천수 공동급수 및 사용료의 징수",
            "온천지구 내 각종 금지행위 지도단속",
            "온천수 급수시설 설치 및 유지관리",
            "그 밖에 온천개발 및 공공시설 유지관리에 관한 사항"
          ],
          "키워드_태그": [
            "도시_건축",
            "경제_산업",
            "문화_교육"
          ],
          "children": []
        },
        {
          "id": "25040.경제문화국.교육과학과",
          "type": "과",
          "name": "교육과학과",
          "level": 2,
          "head_position": "교육과학과장",
          "head_grade": "",
          "정원": null,
          "근거조문": "시행규칙",
          "분장사무_원문": "제19조(교육과학과) 교육과학과장은 다음 사항을 분장한다.1. 초ㆍ중ㆍ고 협력 및 교육지원에 관한 사항2. 외국인 지역적응교육 등 지원3. 학교시설비 지원에 관한 사항4. 청소년육성 종합계획 수립5. 창의적 체험활동 지원6. 청소년 수련시설 및 공부방 운영7. 청소년보호 종합계획 수립8. 청소년 건전프로그램 운영ㆍ지원9. 청소년 방과후 아카데미 운영ㆍ지원10. 대덕연구개발특구 관련 각종행사 업무11. 대덕연구개발특구 연구소 네트워크 구축12. 과학멘토 사업13. 과학축제 개발14. 과학동호인 지원15. 과학기술과 관련된 업무지원16. 디지털 행정혁신 정책 발굴17. 행정 업무절차 간소화 및 시스템 개선 추진18. 디지털전환 지원 인프라 조성 및 운영19. 실증테스트베드 지원20. 디지털포용 사업 추진",
          "분장사무_항목": [
            "초ㆍ중ㆍ고 협력 및 교육지원에 관한 사항",
            "외국인 지역적응교육 등 지원",
            "학교시설비 지원에 관한 사항",
            "청소년육성 종합계획 수립",
            "창의적 체험활동 지원",
            "청소년 수련시설 및 공부방 운영",
            "청소년보호 종합계획 수립",
            "청소년 건전프로그램 운영ㆍ지원",
            "청소년 방과후 아카데미 운영ㆍ지원",
            "대덕연구개발특구 관련 각종행사 업무",
            "대덕연구개발특구 연구소 네트워크 구축",
            "과학멘토 사업",
            "과학축제 개발",
            "과학동호인 지원",
            "과학기술과 관련된 업무지원",
            "디지털 행정혁신 정책 발굴",
            "행정 업무절차 간소화 및 시스템 개선 추진",
            "디지털전환 지원 인프라 조성 및 운영",
            "실증테스트베드 지원",
            "디지털포용 사업 추진"
          ],
          "키워드_태그": [
            "도시_건축",
            "문화_교육"
          ],
          "children": []
        },
        {
          "id": "25040.경제문화국.지역산업과",
          "type": "과",
          "name": "지역산업과",
          "level": 2,
          "head_position": "지역산업과장",
          "head_grade": "",
          "정원": null,
          "근거조문": "시행규칙",
          "분장사무_원문": "제20조(지역산업과) 지역산업과장은 다음 사항을 분장한다.1. 농축산 행정의 종합기획조정2. 식량작물 및 잠업 증산3. 농지개량조합 및 종지개량계 운영지도4. 농업경영인 등 농촌지도자 관리5. 농지업무 및 농업재해6. 농업기반시설 등록등에 관한 사항7. 원예, 과수, 특작, 화훼 증산8. 국유재산 관리9. 농산물 유통 및 수급10. 양정 및 공유수면11. 농기계의 현대화 사업12. 축산업의 등록 및 허가13. 종계업 및 부화업 지도감독14. 가축인공수정소 등록 및 관리15. 초지허가 및 조사료의 생산 수급16. 축산물 생산지도 및 수입축산물 유통지도17. 축산물 판매업, 축산물 운반업 등 신고수리18. 우유급식 업무19. 동물병원, 동물약국 개폐업의 신고수리20. 폐수처리시설의 지원21. 가축 방역 및 가축 전염병 근절22. 축산시설의 현대화23. 가스안전관리 계획수립24. 도시가스(공장등록사항 제외) 및 고압가스에 관한 사항25. 액화석유가스(시공업등록 제외) 및 특정고압가스에 관한 사항26. 에너지관리(소비절약)에 관한 사항27. 연탄 및 석유판매에 관한 사항28. 전기사업자의 전기공사 및 전기설비에 관한 사항29. 전기용품 안전관리에 관한 사항30. 친환경급식 및 로컬푸드에 관한 사항31. 동물 보호 및 복지에 관한 업무",
          "분장사무_항목": [
            "농축산 행정의 종합기획조정",
            "식량작물 및 잠업 증산",
            "농지개량조합 및 종지개량계 운영지도",
            "농업경영인 등 농촌지도자 관리",
            "농지업무 및 농업재해",
            "농업기반시설 등록등에 관한 사항",
            "원예, 과수, 특작, 화훼 증산",
            "국유재산 관리",
            "농산물 유통 및 수급",
            "양정 및 공유수면",
            "농기계의 현대화 사업",
            "축산업의 등록 및 허가",
            "종계업 및 부화업 지도감독",
            "가축인공수정소 등록 및 관리",
            "초지허가 및 조사료의 생산 수급",
            "축산물 생산지도 및 수입축산물 유통지도",
            "축산물 판매업, 축산물 운반업 등 신고수리",
            "우유급식 업무",
            "동물병원, 동물약국 개폐업의 신고수리",
            "폐수처리시설의 지원",
            "가축 방역 및 가축 전염병 근절",
            "축산시설의 현대화",
            "가스안전관리 계획수립",
            "도시가스(공장등록사항 제외) 및 고압가스에 관한 사항",
            "액화석유가스(시공업등록 제외) 및 특정고압가스에 관한 사항",
            "에너지관리(소비절약)에 관한 사항",
            "연탄 및 석유판매에 관한 사항",
            "전기사업자의 전기공사 및 전기설비에 관한 사항",
            "전기용품 안전관리에 관한 사항",
            "친환경급식 및 로컬푸드에 관한 사항",
            "동물 보호 및 복지에 관한 업무"
          ],
          "키워드_태그": [
            "환경",
            "에너지",
            "복지",
            "재난_안전",
            "도시_건축",
            "경제_산업",
            "행정_기획",
            "보건_위생"
          ],
          "children": []
        }
      ]
    },
    {
      "id": "25040.주민복지국",
      "type": "국",
      "name": "주민복지국",
      "level": 1,
      "head_position": "주민복지국장",
      "head_grade": "5급",
      "정원": null,
      "근거조문": "조례 제8조",
      "분장사무_원문": "제8조(주민복지국)① 주민복지국에 사회돌봄과, 노인장애인과, 생활보장과, 아동복지과, 위생과를 둔다. <개정 2024.6.28.>② 주민복지국장은 다음 사항을 분장한다. <개정 2024.6.28.>1. 구민복지시책의 수립ㆍ시행2. 사회복지시설 및 사회복지법인에 관한 업무3. 아동학대 및 아동보호에 관한 사항4. 아동친화사업 추진5. 초등 방과후 돌봄 지원6. 식품 및 공중위생 업무[전문개정 2023.2.6.]",
      "분장사무_항목": [
        "구민복지시책의 수립ㆍ시행",
        "사회복지시설 및 사회복지법인에 관한 업무",
        "아동학대 및 아동보호에 관한 사항",
        "아동친화사업 추진",
        "초등 방과후 돌봄 지원",
        "식품 및 공중위생 업무[전문개정 2023.2.6.]"
      ],
      "키워드_태그": [
        "복지",
        "보건_위생"
      ],
      "children": [
        {
          "id": "25040.주민복지국.사회돌봄과",
          "type": "과",
          "name": "사회돌봄과",
          "level": 2,
          "head_position": "사회돌봄과장",
          "head_grade": "",
          "정원": null,
          "근거조문": "시행규칙",
          "분장사무_원문": "제22조(사회돌봄과) 사회돌봄과장은 다음 사항을 분장한다.1. 복지정책계획 수립ㆍ조정2. 지역사회보장계획 수립 및 평가3. 지자체 복지정책 평가4. 지역사회서비스투자사업5. 사회복지전담공무원 관련업무6. 사회복지시설 근무 사회복무요원 관리7. 보훈단체 지원에 관한 사항(구지부)8. 구 종합복지관, 송강사회복지관 보조금 지원업무, 행사 및 지도점검9. 식품기부 활성화 업무10. 지역사회 통합돌봄사업11. 여성능력개발사업 및 여성단체 육성12. 한부모가족 및 다문화가족 지원 및 관리13. 성폭력ㆍ가정폭력ㆍ성매매방지 및 피해자 보호사업14. 건강가정 운영관련 업무15. 성별영향분석평가에 관한 사항16. 결혼중개업(국내ㆍ외)에 관한 사항17. 저출산 관련 업무18. 여성친화사업 추진 총괄 및 관리19. 아이돌봄지원사업",
          "분장사무_항목": [
            "복지정책계획 수립ㆍ조정",
            "지역사회보장계획 수립 및 평가",
            "지자체 복지정책 평가",
            "지역사회서비스투자사업",
            "사회복지전담공무원 관련업무",
            "사회복지시설 근무 사회복무요원 관리",
            "보훈단체 지원에 관한 사항(구지부)",
            "구 종합복지관, 송강사회복지관 보조금 지원업무, 행사 및 지도점검",
            "식품기부 활성화 업무",
            "지역사회 통합돌봄사업",
            "여성능력개발사업 및 여성단체 육성",
            "한부모가족 및 다문화가족 지원 및 관리",
            "성폭력ㆍ가정폭력ㆍ성매매방지 및 피해자 보호사업",
            "건강가정 운영관련 업무",
            "성별영향분석평가에 관한 사항",
            "결혼중개업(국내ㆍ외)에 관한 사항",
            "저출산 관련 업무",
            "여성친화사업 추진 총괄 및 관리",
            "아이돌봄지원사업"
          ],
          "키워드_태그": [
            "복지",
            "도시_건축",
            "문화_교육"
          ],
          "children": []
        },
        {
          "id": "25040.주민복지국.노인장애인과",
          "type": "과",
          "name": "노인장애인과",
          "level": 2,
          "head_position": "노인장애인과장",
          "head_grade": "",
          "정원": null,
          "근거조문": "시행규칙",
          "분장사무_원문": "제23조(노인장애인과) 노인장애인과장은 다음 사항을 분장한다.1. 노인복지정책 계획 및 노인회지회 관련 운영 지원 업무2. 경로당 등록 등 관련업무3. 유연 및 무연 매장ㆍ화장ㆍ장사관련 업무4. 노인복지시설 관련 지원 및 관리업무5. 노인장기요양보험관련 업무6. 노인일자리 및 기초연금 관련 업무7. 장애인관련 종합계획 수립 및 조정에 관한 사항8. 장애인 복지시설 설치ㆍ운영ㆍ행사ㆍ지도점검 등 지원에 관한 사항(유성구 장애인종합복지관 포함)9. 장애인 복지에 관한 사항10. 장애인 차별금지 및 권리구제에 관한 사항11. 장애인 관련단체 운영지원에 관한 사항12. 장애인 일자리관련 업무13. 4대 사회복지시설 및 그 밖에 복지시설 기능보강사업 및 안전점검14. 노인복지시설(유성구 노인복지관 포함) 설치ㆍ운영ㆍ행사ㆍ지도점검 등 지원에 관한 사항",
          "분장사무_항목": [
            "노인복지정책 계획 및 노인회지회 관련 운영 지원 업무",
            "경로당 등록 등 관련업무",
            "유연 및 무연 매장ㆍ화장ㆍ장사관련 업무",
            "노인복지시설 관련 지원 및 관리업무",
            "노인장기요양보험관련 업무",
            "노인일자리 및 기초연금 관련 업무",
            "장애인관련 종합계획 수립 및 조정에 관한 사항",
            "장애인 복지시설 설치ㆍ운영ㆍ행사ㆍ지도점검 등 지원에 관한 사항(유성구 장애인종합복지관 포함)",
            "장애인 복지에 관한 사항",
            "장애인 차별금지 및 권리구제에 관한 사항",
            "장애인 관련단체 운영지원에 관한 사항",
            "장애인 일자리관련 업무",
            "4대 사회복지시설 및 그 밖에 복지시설 기능보강사업 및 안전점검",
            "노인복지시설(유성구 노인복지관 포함) 설치ㆍ운영ㆍ행사ㆍ지도점검 등 지원에 관한 사항"
          ],
          "키워드_태그": [
            "복지",
            "재난_안전"
          ],
          "children": []
        },
        {
          "id": "25040.주민복지국.생활보장과",
          "type": "과",
          "name": "생활보장과",
          "level": 2,
          "head_position": "생활보장과장",
          "head_grade": "",
          "정원": null,
          "근거조문": "시행규칙",
          "분장사무_원문": "제24조(생활보장과) 생활보장과장은 다음 사항을 분장한다.1. 지역사회복지협의체 구성ㆍ운영2. 기초생활보장수급자 조사(관리) 및 급여지원3. 기초연금대상자 조사 및 관리4. 보육대상자(보육료, 양육수당)조사 및 관리5. 한부모가족지원 조사 및 관리6. (차상위계층)장애수당, 장애아동수당, 장애인자녀교육비 조사 및 관리7. (차상위계층)의료급여 조사 및 관리8. (차상위계층)자활지원 조사 및 관리9. 긴급복지지원 조사10. 사회취약계층 조사 및 관리11. 희귀ㆍ난치성질환, 암환자 조사12. 지역사회 자원의 발굴 및 관리13. 사회복지서비스 연계14. 긴급복지지원사업15. 민생안정지원사업16. 복지만두레 관련 업무17. 의료급여 전반18. 의료급여특별회계 관리19. 의료급여수급자 사례관리20. 무연고 사망자(행여) 장제처리21. 자활사업 관리 업무22. 저소득층 사례관리23. 저소득층 지원기금 및 자금의 지원관리24. 저소득 특별지원사업 관련 업무25. 저소득 장학기금 관리",
          "분장사무_항목": [
            "지역사회복지협의체 구성ㆍ운영",
            "기초생활보장수급자 조사(관리) 및 급여지원",
            "기초연금대상자 조사 및 관리",
            "보육대상자(보육료, 양육수당)조사 및 관리",
            "한부모가족지원 조사 및 관리",
            "(차상위계층)장애수당, 장애아동수당, 장애인자녀교육비 조사 및 관리",
            "(차상위계층)의료급여 조사 및 관리",
            "(차상위계층)자활지원 조사 및 관리",
            "긴급복지지원 조사",
            "사회취약계층 조사 및 관리",
            "희귀ㆍ난치성질환, 암환자 조사",
            "지역사회 자원의 발굴 및 관리",
            "사회복지서비스 연계",
            "긴급복지지원사업",
            "민생안정지원사업",
            "복지만두레 관련 업무",
            "의료급여 전반",
            "의료급여특별회계 관리",
            "의료급여수급자 사례관리",
            "무연고 사망자(행여) 장제처리",
            "자활사업 관리 업무",
            "저소득층 사례관리",
            "저소득층 지원기금 및 자금의 지원관리",
            "저소득 특별지원사업 관련 업무",
            "저소득 장학기금 관리"
          ],
          "키워드_태그": [
            "복지",
            "문화_교육",
            "보건_위생"
          ],
          "children": []
        },
        {
          "id": "25040.주민복지국.아동복지과",
          "type": "과",
          "name": "아동복지과",
          "level": 2,
          "head_position": "아동복지과장",
          "head_grade": "",
          "정원": null,
          "근거조문": "시행규칙",
          "분장사무_원문": "제25조(아동복지과) 아동복지과장은 다음 사항을 분장한다.1. 요보호아동 보호ㆍ지원 및 관리2. 아동복지시설 기능보강 및 운영지원3. 아동발달지원계좌 사업4. 결식아동 급식지원사업5. 빈곤아동의 맞춤형 통합서비스 지원6. 보육사업 시행계획 수립에 과한 사항7. 보육통합시스템 운영(아이사랑카드)에 관한 사항8. 보육료 지원에 관한 사항9. 어린이집 보조금 지원에 관한 사항10. 어린이집 미이용 아동 양육비 지원11. 어린이집 평가 인증에 관한 사항12. 보육도우미에 관한 사항13. 유성구 영ㆍ유아 보육지원센터 운영14. 어린이집 수급계획 수립에 관한 사항15. 민간ㆍ가정ㆍ직장ㆍ국공립보육시설 설치 및 폐지16. 어린이집 지도ㆍ점검에 관한 사항17. 보육 교직원(임면, 재직, 경력) 관리18. 아동친화사업 추진 총괄 및 관리19. 초등 방과후 돌봄 지원에 관한 사항",
          "분장사무_항목": [
            "요보호아동 보호ㆍ지원 및 관리",
            "아동복지시설 기능보강 및 운영지원",
            "아동발달지원계좌 사업",
            "결식아동 급식지원사업",
            "빈곤아동의 맞춤형 통합서비스 지원",
            "보육사업 시행계획 수립에 과한 사항",
            "보육통합시스템 운영(아이사랑카드)에 관한 사항",
            "보육료 지원에 관한 사항",
            "어린이집 보조금 지원에 관한 사항",
            "어린이집 미이용 아동 양육비 지원",
            "어린이집 평가 인증에 관한 사항",
            "보육도우미에 관한 사항",
            "유성구 영ㆍ유아 보육지원센터 운영",
            "어린이집 수급계획 수립에 관한 사항",
            "민간ㆍ가정ㆍ직장ㆍ국공립보육시설 설치 및 폐지",
            "어린이집 지도ㆍ점검에 관한 사항",
            "보육 교직원(임면, 재직, 경력) 관리",
            "아동친화사업 추진 총괄 및 관리",
            "초등 방과후 돌봄 지원에 관한 사항"
          ],
          "키워드_태그": [
            "복지"
          ],
          "children": []
        },
        {
          "id": "25040.주민복지국.위생과",
          "type": "과",
          "name": "위생과",
          "level": 2,
          "head_position": "위생과장",
          "head_grade": "",
          "정원": null,
          "근거조문": "시행규칙",
          "분장사무_원문": "제26조(위생과) 위생과장은 다음사항을 분장한다.1. 식품ㆍ공중위생업소의 종합지도2. 식품ㆍ공중위생업소의 허가 및 지도감독3. 영양사, 조리사, 식품위생업소 종업원 지도4. 식품진흥기금에 관한 사항5. 위생업자 교육6. 위생업소의 지도감독 및 행정처분7. 무허가ㆍ퇴폐ㆍ변태업소 단속8. 부정ㆍ불량식품 단속처리9. 식중독 조사관리10. 위생용품 및 식품에 대한 검사와 품질관리11. 포장마차 등의 음식물(부정ㆍ불량식품포함) 판매행위에 대한 고발 등 지도ㆍ단속에 관한 사항",
          "분장사무_항목": [
            "식품ㆍ공중위생업소의 종합지도",
            "식품ㆍ공중위생업소의 허가 및 지도감독",
            "영양사, 조리사, 식품위생업소 종업원 지도",
            "식품진흥기금에 관한 사항",
            "위생업자 교육",
            "위생업소의 지도감독 및 행정처분",
            "무허가ㆍ퇴폐ㆍ변태업소 단속",
            "부정ㆍ불량식품 단속처리",
            "식중독 조사관리",
            "위생용품 및 식품에 대한 검사와 품질관리",
            "포장마차 등의 음식물(부정ㆍ불량식품포함) 판매행위에 대한 고발 등 지도ㆍ단속에 관한 사항"
          ],
          "키워드_태그": [
            "문화_교육",
            "보건_위생"
          ],
          "children": []
        }
      ]
    },
    {
      "id": "25040.생활환경국",
      "type": "국",
      "name": "생활환경국",
      "level": 1,
      "head_position": "생활환경국장",
      "head_grade": "5급",
      "정원": null,
      "근거조문": "조례 제8조의2",
      "분장사무_원문": "제8조의2(생활환경국)① 생활환경국에 푸른환경과, 청소행정과, 교통정책과, 주차관리과, 공원과, 녹지산림과를 둔다.② 생활환경국장은 다음 사항을 분장한다.1. 환경보존 대책수립2. 상수원보호구역, 간이급수시설, 저수조, 중수도관리에 관한 사항3. 오수 분뇨 및 쓰레기 처리4. 쓰레기 수수료 종량제 및 자연보호에 관한 사항5. 녹색성장업무6. 교통행정의 종합계획 및 조정7. 교통시설 및 주차장 관리8. 자동차 관리 및 운송사업에 관한 사항9. 국토 및 자연자원의 보존 및 이용10. 도시녹화사업 및 산림보호11. 공원관리 및 녹지사업 추진12. 산림업무 추진13. 공원, 공영주차장 내의 장애물(노점상, 적치물, 포장마차 등)의 정리를 위한 합동단속 및 지도ㆍ감독에 관한 사항[본조신설 2020.7.8.]",
      "분장사무_항목": [
        "환경보존 대책수립",
        "상수원보호구역, 간이급수시설, 저수조, 중수도관리에 관한 사항",
        "오수 분뇨 및 쓰레기 처리",
        "쓰레기 수수료 종량제 및 자연보호에 관한 사항",
        "녹색성장업무",
        "교통행정의 종합계획 및 조정",
        "교통시설 및 주차장 관리",
        "자동차 관리 및 운송사업에 관한 사항",
        "국토 및 자연자원의 보존 및 이용",
        "도시녹화사업 및 산림보호",
        "공원관리 및 녹지사업 추진",
        "산림업무 추진",
        "공원, 공영주차장 내의 장애물(노점상, 적치물, 포장마차 등)의 정리를 위한 합동단속 및 지도ㆍ감독에 관한 사항[본조신설 2020.7.8.]"
      ],
      "키워드_태그": [
        "환경",
        "녹지_생태",
        "교통",
        "복지",
        "도시_건축"
      ],
      "children": [
        {
          "id": "25040.생활환경국.푸른환경과",
          "type": "과",
          "name": "푸른환경과",
          "level": 2,
          "head_position": "푸른환경과장",
          "head_grade": "",
          "정원": null,
          "근거조문": "조례",
          "분장사무_원문": "제28조(푸른환경과) 푸른환경과장은 다음 사항을 분장한다.1. 환경보전 종합계획 수립2. 환경ㆍ교통ㆍ재해 등에 관한 영향평가 관리3. 환경개선비용부담금 관리4. 자연환경보전업무 추진5. 야생동물보호 및 관리 지원6. 소음ㆍ진동(공장, 생활, 교통) 규제7. 폐수의 배출규제(산업단지 제외)8. 공공수역의 수질보전9. 먹는물의 공동시설(약수터) 관리10. 유통되는 먹는샘물 수거검사11. 토양오염의 규제12. 토양보전대책지역의 지정 및 관리13. 사업장 등의 대기오염물질 배출규제(산업단지 제외)14. 생활환경상의 대기오염물질 배출규제(산업단지 제외)15. 자동차 배출가스의 규제16. 가축ㆍ분뇨 배출시설의 관리17. 환경측정기기의 관리18. 환경배출시설(대기, 수질, 소음, 진동) 인ㆍ허가 등19. 냉ㆍ온수기, 정수기 관리20. 환경단체 관리21. 기후변화적응대책 세부시행계획 수립22. 녹색성장 실행계획 수립23. 저탄소 친환경생활 실천 주민 홍보24. 그린리더 육성 및 운영25. 다중이용시설 및 신축공동주택의 실내공기질 측정 등 관리26. 어린이활동공간 지도ㆍ점검27. 오존경보제 운영28. 지방의제21 추진에 관한 사항29. 분뇨관련영업허가 등 관리 및 처리30. 공중화장실 청소 관리31. 가축ㆍ분뇨 관련 영업관리32. 개인하수처리시설 관련 영업 관리33. 저수조청소업 관리34. 절수설비 및 중수도 관리35. 개인하수처리시설(오수, 정화조) 관리36. 환경사법경찰관 관리ㆍ운영",
          "분장사무_항목": [
            "환경보전 종합계획 수립",
            "환경ㆍ교통ㆍ재해 등에 관한 영향평가 관리",
            "환경개선비용부담금 관리",
            "자연환경보전업무 추진",
            "야생동물보호 및 관리 지원",
            "소음ㆍ진동(공장, 생활, 교통) 규제",
            "폐수의 배출규제(산업단지 제외)",
            "공공수역의 수질보전",
            "먹는물의 공동시설(약수터) 관리",
            "유통되는 먹는샘물 수거검사",
            "토양오염의 규제",
            "토양보전대책지역의 지정 및 관리",
            "사업장 등의 대기오염물질 배출규제(산업단지 제외)",
            "생활환경상의 대기오염물질 배출규제(산업단지 제외)",
            "자동차 배출가스의 규제",
            "가축ㆍ분뇨 배출시설의 관리",
            "환경측정기기의 관리",
            "환경배출시설(대기, 수질, 소음, 진동) 인ㆍ허가 등",
            "냉ㆍ온수기, 정수기 관리",
            "환경단체 관리",
            "기후변화적응대책 세부시행계획 수립",
            "녹색성장 실행계획 수립",
            "저탄소 친환경생활 실천 주민 홍보",
            "그린리더 육성 및 운영",
            "다중이용시설 및 신축공동주택의 실내공기질 측정 등 관리",
            "어린이활동공간 지도ㆍ점검",
            "오존경보제 운영",
            "지방의제21 추진에 관한 사항",
            "분뇨관련영업허가 등 관리 및 처리",
            "공중화장실 청소 관리",
            "가축ㆍ분뇨 관련 영업관리",
            "개인하수처리시설 관련 영업 관리",
            "저수조청소업 관리",
            "절수설비 및 중수도 관리",
            "개인하수처리시설(오수, 정화조) 관리",
            "환경사법경찰관 관리ㆍ운영"
          ],
          "키워드_태그": [
            "기후",
            "환경",
            "교통",
            "도시_건축",
            "경제_산업"
          ],
          "children": []
        },
        {
          "id": "25040.생활환경국.청소행정과",
          "type": "과",
          "name": "청소행정과",
          "level": 2,
          "head_position": "청소행정과장",
          "head_grade": "",
          "정원": null,
          "근거조문": "조례",
          "분장사무_원문": "제29조(청소행정과) 청소행정과장은 다음 사항을 분장한다.1. 폐기물 관리 종합 추진2. 폐기물의 배출 및 처리3. 생활폐기물 관리4. 음식물류폐기물 관리5. 사업장(지정외)폐기물 관리6. 지정폐기물 처리의 증명7. 폐기물처리업 등8. 폐기물 처리시설등 관리9. 폐기물처리업자등에 대한 지도ㆍ감독등10. 택지개발사업에 따른 폐기물처리시설 설치등11. 자원의절약과 재활용촉진12. 폐기물 재활용 촉진13. 석면 안전관리14. 석면피해구제급여 지원사업 추진15. 건설폐기물 관리16. 환경사법경찰관 관리ㆍ운영17. 환경관리요원의 임면ㆍ복무관리 등18. 환경노동조합에 관한 사항19. 환경노동조합 단체교섭 및 단체ㆍ임금협약에 관한 사항",
          "분장사무_항목": [
            "폐기물 관리 종합 추진",
            "폐기물의 배출 및 처리",
            "생활폐기물 관리",
            "음식물류폐기물 관리",
            "사업장(지정외)폐기물 관리",
            "지정폐기물 처리의 증명",
            "폐기물처리업 등",
            "폐기물 처리시설등 관리",
            "폐기물처리업자등에 대한 지도ㆍ감독등",
            "택지개발사업에 따른 폐기물처리시설 설치등",
            "자원의절약과 재활용촉진",
            "폐기물 재활용 촉진",
            "석면 안전관리",
            "석면피해구제급여 지원사업 추진",
            "건설폐기물 관리",
            "환경사법경찰관 관리ㆍ운영",
            "환경관리요원의 임면ㆍ복무관리 등",
            "환경노동조합에 관한 사항",
            "환경노동조합 단체교섭 및 단체ㆍ임금협약에 관한 사항"
          ],
          "키워드_태그": [
            "환경",
            "재난_안전",
            "도시_건축"
          ],
          "children": []
        },
        {
          "id": "25040.생활환경국.교통정책과",
          "type": "과",
          "name": "교통정책과",
          "level": 2,
          "head_position": "교통정책과장",
          "head_grade": "",
          "정원": null,
          "근거조문": "조례",
          "분장사무_원문": "제30조(교통정책과) 교통정책과장은 다음 사항을 분장한다.1. 교통유발부담금의 부과 징수2. 교통체계 관리 및 교통시설 유지관리3. 자동차 정류장 사업 및 창고업4. 동원차량에 관한 사항5. 교통영향평가 업무6. 자동차 운송사업 한정면허(마을버스)7. 화물자동차, 개인택시운송사업의 인ㆍ허가 및 지도감독8. 자동차운송 알선업 등록 및 지도감독9. 택시운송 사업시설 확인 및 지도감독10. 자동차 관리사업 지도감독11. 법규위반차량 단속 및 업무지도 감독12. 이륜 소형자동차 업무13. 자동차 매매업, 책임보험에 관한 사항14. 건설기계 신고ㆍ동원에 관한 사항15. 자동차 등록원부 발급에 관한 사무16. 자가용화물자동차 사용에 관한 사항17. 특수여객자동차(장의자동차) 운송시설 확인18. 「여객자동차 운수사업법」 및 화물자동차 과태료 부과 징수19. 여객자동차운수사업자에 대한 보고, 검사 등20. 여객자동차 터미널사업에 관한 사항21. 항공장애등 설치 및 관리",
          "분장사무_항목": [
            "교통유발부담금의 부과 징수",
            "교통체계 관리 및 교통시설 유지관리",
            "자동차 정류장 사업 및 창고업",
            "동원차량에 관한 사항",
            "교통영향평가 업무",
            "자동차 운송사업 한정면허(마을버스)",
            "화물자동차, 개인택시운송사업의 인ㆍ허가 및 지도감독",
            "자동차운송 알선업 등록 및 지도감독",
            "택시운송 사업시설 확인 및 지도감독",
            "자동차 관리사업 지도감독",
            "법규위반차량 단속 및 업무지도 감독",
            "이륜 소형자동차 업무",
            "자동차 매매업, 책임보험에 관한 사항",
            "건설기계 신고ㆍ동원에 관한 사항",
            "자동차 등록원부 발급에 관한 사무",
            "자가용화물자동차 사용에 관한 사항",
            "특수여객자동차(장의자동차) 운송시설 확인",
            "「여객자동차 운수사업법」 및 화물자동차 과태료 부과 징수",
            "여객자동차운수사업자에 대한 보고, 검사 등",
            "여객자동차 터미널사업에 관한 사항",
            "항공장애등 설치 및 관리"
          ],
          "키워드_태그": [
            "교통",
            "복지"
          ],
          "children": []
        },
        {
          "id": "25040.생활환경국.주차관리과",
          "type": "과",
          "name": "주차관리과",
          "level": 2,
          "head_position": "주차관리과장",
          "head_grade": "",
          "정원": null,
          "근거조문": "조례",
          "분장사무_원문": "제31조(주차관리과) 주차관리과장은 다음 사항을 분장한다.1. 교통질서 및 주차 종합계획 수립2. 불법주ㆍ정차 단속 및 과태료 부과, 민원처리에 관한 사항3. 주정차 단속요원 관리4. 주차시설의 확충 및 관리5. 공영주차장 조성 및 관리6. 수통골 지역의 주차장 관리7. 유성IㆍC 만남의 장소 유지관리8. 공영주차장내의 장애물(노점상, 적치물, 포장마차)의 단속ㆍ정리9. 주차장 적립기금 관리10. 교통체납에 관한 사항",
          "분장사무_항목": [
            "교통질서 및 주차 종합계획 수립",
            "불법주ㆍ정차 단속 및 과태료 부과, 민원처리에 관한 사항",
            "주정차 단속요원 관리",
            "주차시설의 확충 및 관리",
            "공영주차장 조성 및 관리",
            "수통골 지역의 주차장 관리",
            "유성IㆍC 만남의 장소 유지관리",
            "공영주차장내의 장애물(노점상, 적치물, 포장마차)의 단속ㆍ정리",
            "주차장 적립기금 관리",
            "교통체납에 관한 사항"
          ],
          "키워드_태그": [
            "교통",
            "복지"
          ],
          "children": []
        },
        {
          "id": "25040.생활환경국.공원과",
          "type": "과",
          "name": "공원과",
          "level": 2,
          "head_position": "공원과장",
          "head_grade": "",
          "정원": null,
          "근거조문": "조례",
          "분장사무_원문": "제32조(공원과) 공원과장은 다음 사항을 분장한다.1. 도시공원 조성계획 입안ㆍ결정ㆍ고시에 관한 사항2. 도시공원 및 녹지의 조성ㆍ관리에 관한 사항3. 공원이용 활성화 및 프로그램 개발에 관한 사항4. 도시공원(유원지) 조경관리 및 시설물 유지관리5. 어린이공원의 조경관리 및 놀이시설 관리6. 도시개발사업 등에 따른 공원ㆍ녹지시설 조성협의 및 인수ㆍ인계7. 어린이물놀이장, 눈썰매장 등 시책사업 추진",
          "분장사무_항목": [
            "도시공원 조성계획 입안ㆍ결정ㆍ고시에 관한 사항",
            "도시공원 및 녹지의 조성ㆍ관리에 관한 사항",
            "공원이용 활성화 및 프로그램 개발에 관한 사항",
            "도시공원(유원지) 조경관리 및 시설물 유지관리",
            "어린이공원의 조경관리 및 놀이시설 관리",
            "도시개발사업 등에 따른 공원ㆍ녹지시설 조성협의 및 인수ㆍ인계",
            "어린이물놀이장, 눈썰매장 등 시책사업 추진"
          ],
          "키워드_태그": [
            "녹지_생태",
            "도시_건축"
          ],
          "children": []
        },
        {
          "id": "25040.생활환경국.녹지산림과",
          "type": "과",
          "name": "녹지산림과",
          "level": 2,
          "head_position": "녹지산림과장",
          "head_grade": "",
          "정원": null,
          "근거조문": "조례",
          "분장사무_원문": "제33조(녹지산림과) 녹지산림과장은 다음 사항을 분장한다.1. 도시공간 녹화계획 수립 및 조성에 관한 사항2. 도시림 조성계획 및 시행에 관한 사항3. 녹지대 조성 및 관리4. 가로수 식재 및 관리5. 공공시설 녹화 및 건축조경에 관한 사항6. 화훼포 및 양묘장 운영에 관한사항7. 녹지기금의 조성 및 운영8. 산림자원의 조성 및 육성과 이용에 관한 사항9. 조림 및 숲가꾸기에 관한 사항10. 산불예방과 진화ㆍ복구에 관한 사항11. 임산물관리 및 육성에 관한 사항12. 등산로(임도)조성 및 관리에 관한 사항13. 산림통계 작성관리14. 산림욕장 및 자연휴양림 조성 관리15. 동ㆍ식물원 조성 및 관리",
          "분장사무_항목": [
            "도시공간 녹화계획 수립 및 조성에 관한 사항",
            "도시림 조성계획 및 시행에 관한 사항",
            "녹지대 조성 및 관리",
            "가로수 식재 및 관리",
            "공공시설 녹화 및 건축조경에 관한 사항",
            "화훼포 및 양묘장 운영에 관한사항",
            "녹지기금의 조성 및 운영",
            "산림자원의 조성 및 육성과 이용에 관한 사항",
            "조림 및 숲가꾸기에 관한 사항",
            "산불예방과 진화ㆍ복구에 관한 사항",
            "임산물관리 및 육성에 관한 사항",
            "등산로(임도)조성 및 관리에 관한 사항",
            "산림통계 작성관리",
            "산림욕장 및 자연휴양림 조성 관리",
            "동ㆍ식물원 조성 및 관리"
          ],
          "키워드_태그": [
            "녹지_생태",
            "도시_건축"
          ],
          "children": []
        }
      ]
    },
    {
      "id": "25040.안전도시국",
      "type": "국",
      "name": "안전도시국",
      "level": 1,
      "head_position": "안전도시국장",
      "head_grade": "5급",
      "정원": null,
      "근거조문": "조례 제9조",
      "분장사무_원문": "제9조(안전도시국)① 안전도시국에 도시계획과, 재난안전과, 건설과, 건축과, 공동주택과를 둔다. <개정 2024.6.28.>② 안전도시국장은 다음 사항을 분장한다.1. 도시정비계획에 관한 사항2. 개발제한구역의 관리3. 안전 및 재난관리 총괄4. 민방위 종합계획 수립시행5. 민방위 대원 조직편성 및 훈련 등6. 국가기반체계보호에 관한 사항7. 도로, 하천, 공유수면 관리8. 생활민원의 처리9. 나대지, 도로 내의 장애물(노점상, 적치물, 포장마차 등)의 정리를 위한 합동단속 및 지도ㆍ감독에 관한 사항10. 토목, 건설사업의 시행11. 하수행정에 관한 사항12. 건축물 허가 및 불법건축물 단속13. 광고물 관리14. 공동주택 지도ㆍ감독 업무15. 공동주택 지원에 관한 업무16. 삭제 <2024.6.28.>17. 삭제 <2024.6.28.>18. 삭제 <2024.6.28.>19. 삭제 <2024.6.28.>20. 삭제 <2024.6.28.>[전문개정 2023.2.6.]",
      "분장사무_항목": [
        "도시정비계획에 관한 사항",
        "개발제한구역의 관리",
        "안전 및 재난관리 총괄",
        "민방위 종합계획 수립시행",
        "민방위 대원 조직편성 및 훈련 등",
        "국가기반체계보호에 관한 사항",
        "도로, 하천, 공유수면 관리",
        "생활민원의 처리",
        "나대지, 도로 내의 장애물(노점상, 적치물, 포장마차 등)의 정리를 위한 합동단속 및 지도ㆍ감독에 관한 사항",
        "토목, 건설사업의 시행",
        "하수행정에 관한 사항",
        "건축물 허가 및 불법건축물 단속",
        "광고물 관리",
        "공동주택 지도ㆍ감독 업무",
        "공동주택 지원에 관한 업무",
        "삭제 [전문개정 2023.2.6.]"
      ],
      "키워드_태그": [
        "교통",
        "복지",
        "재난_안전",
        "도시_건축"
      ],
      "children": [
        {
          "id": "25040.안전도시국.도시계획과",
          "type": "과",
          "name": "도시계획과",
          "level": 2,
          "head_position": "도시계획과장",
          "head_grade": "",
          "정원": null,
          "근거조문": "시행규칙",
          "분장사무_원문": "제35조(도시계획과) 도시계획과장은 다음 사항을 분장한다.1. 도시계획에 관한 사항2. 도시계획선 명시측량3. 개발제한구역 관리4. 주거환경개선사업 및 도심지 재개발5. 토지구획정리사업 및 택지개발사업6. 토지형질변경 관련 업무7. 개발제한구역의 불법행위 지도ㆍ단속에 관한 사항8. 도시재생사업에 관한 사항",
          "분장사무_항목": [
            "도시계획에 관한 사항",
            "도시계획선 명시측량",
            "개발제한구역 관리",
            "주거환경개선사업 및 도심지 재개발",
            "토지구획정리사업 및 택지개발사업",
            "토지형질변경 관련 업무",
            "개발제한구역의 불법행위 지도ㆍ단속에 관한 사항",
            "도시재생사업에 관한 사항"
          ],
          "키워드_태그": [
            "환경",
            "도시_건축"
          ],
          "children": []
        },
        {
          "id": "25040.안전도시국.재난안전과",
          "type": "과",
          "name": "재난안전과",
          "level": 2,
          "head_position": "재난안전과장",
          "head_grade": "",
          "정원": null,
          "근거조문": "시행규칙",
          "분장사무_원문": "제36조(재난안전과) 재난안전과장은 다음 사항을 분장한다. <개정 2024.12.31.>1. 안전관리계획 등 각종 계획 수립2. 지역재난안전대책본부 운영3. 재난관리체계 등 정비ㆍ평가에 관한 사항4. 재난관리기금의 적립ㆍ운용ㆍ지출ㆍ결산 등에 관한 사항5. 재난예방 교육ㆍ훈련ㆍ홍보에 관한 사항6. 국가안전관리정보시스템 관리 총괄7. 재난상황 관리ㆍ동향관리8. 자연재난 업무 총괄9. 소하천의 정비 및 관리10. 자연재난예방 및 피해 저감을 위한 검토ㆍ협의11. 자연재난관련 민간협력 지원12. 우수유출저감대책 등 재해관련 각종대책 수립13. 인적재난 업무 총괄14. 재난대비 물자ㆍ재원ㆍ장비관리 및 동원계획 수립15. 재난대비 훈련 실시 및 평가16. 재난관련 유관기관 협조체계 구축17. 안전관리자문단 운영18. 재난예방시설 설치 및 위험지역 지정ㆍ점검19. 재난관련 응급복구용 장비 지정ㆍ관리20. 안전관리체계 구축21. 각종 시설물의 안전관리 총괄22. 응급조치 및 이재민 지원23. 재난상황 대처요령 작성24. 안전관련 봉사단체 등 관리25. 안전점검의 행사 등 안전문화운동 관련 업무26. 민방위 업무 종합기획ㆍ조정27. 민방위 시설물 및 장비 관리ㆍ동원 등28. 충무계획의 수립시행29. 민방위대 편성ㆍ관리ㆍ동원 및 교육ㆍ훈련 실시30. 공익근무요원의 복무 및 관리에 관한 사항31. 전시 인력동원에 관한 사항32. 민방위 사태하의 주민소산 및 수송통제33. 민방위상황실 운영 및 각급 기관협조34. 국가기반체계보호 종합상황실 설치ㆍ운영35. 국가기반체계보호 재난상황의 보고36. 국가기반체계보호관련 안전관리계획 수립ㆍ집행37. 국가기반체계보호관련 재난의 예방조치, 예ㆍ경보 발령38. 국가기반체계보호관련 지역안전관리위원회 및 지역안전대책본부 구성ㆍ운영39. 국가기반체계보호관련 인력ㆍ장비ㆍ물자 등의 동원명령40. 국가기반체계보호관련 특별재난지역에 대한 지원 등41. 국가기반체계보호관련 위험지구 설정42. 국가기반체계보호관련 대피명령ㆍ강제대피조치ㆍ통행제한ㆍ응원ㆍ응급부담 등43. 수상레저에 관한 사항44. 구 통합방위협의회 운영45. 하천관리(사용료, 기본자료조사, 수익자 부담금 징수 포함)46. 하천공작물, 하천골재채취 허가47. 하천공사의 조사, 측량, 설계48. 지방하천 정비 기본계획 수립49. 하천 편입토지 보상 및 폐천부지 관리50. 안전정책 총괄ㆍ조정51. 안전문화운동, 안전공동체 육성에 관한 사항52. 안전지수, 안전지도에 관한 사항53. 안전수준 진단ㆍ분석에 관한 사항54. 승강기 제도 및 관리 업무55. 원자력시설 인근 지역 주민보호 업무56. 지역방사능 방재계획수립 시행57. 방사능 방재대책본부 구성 및 운영58. 방사능 방재훈련59. 방사선비상계획구역 설정 관련 업무60. 중대재해 예방에 관한 사항",
          "분장사무_항목": [
            "안전관리계획 등 각종 계획 수립",
            "지역재난안전대책본부 운영",
            "재난관리체계 등 정비ㆍ평가에 관한 사항",
            "재난관리기금의 적립ㆍ운용ㆍ지출ㆍ결산 등에 관한 사항",
            "재난예방 교육ㆍ훈련ㆍ홍보에 관한 사항",
            "국가안전관리정보시스템 관리 총괄",
            "재난상황 관리ㆍ동향관리",
            "자연재난 업무 총괄",
            "소하천의 정비 및 관리",
            "자연재난예방 및 피해 저감을 위한 검토ㆍ협의",
            "자연재난관련 민간협력 지원",
            "우수유출저감대책 등 재해관련 각종대책 수립",
            "인적재난 업무 총괄",
            "재난대비 물자ㆍ재원ㆍ장비관리 및 동원계획 수립",
            "재난대비 훈련 실시 및 평가",
            "재난관련 유관기관 협조체계 구축",
            "안전관리자문단 운영",
            "재난예방시설 설치 및 위험지역 지정ㆍ점검",
            "재난관련 응급복구용 장비 지정ㆍ관리",
            "안전관리체계 구축",
            "각종 시설물의 안전관리 총괄",
            "응급조치 및 이재민 지원",
            "재난상황 대처요령 작성",
            "안전관련 봉사단체 등 관리",
            "안전점검의 행사 등 안전문화운동 관련 업무",
            "민방위 업무 종합기획ㆍ조정",
            "민방위 시설물 및 장비 관리ㆍ동원 등",
            "충무계획의 수립시행",
            "민방위대 편성ㆍ관리ㆍ동원 및 교육ㆍ훈련 실시",
            "공익근무요원의 복무 및 관리에 관한 사항",
            "전시 인력동원에 관한 사항",
            "민방위 사태하의 주민소산 및 수송통제",
            "민방위상황실 운영 및 각급 기관협조",
            "국가기반체계보호 종합상황실 설치ㆍ운영",
            "국가기반체계보호 재난상황의 보고",
            "국가기반체계보호관련 안전관리계획 수립ㆍ집행",
            "국가기반체계보호관련 재난의 예방조치, 예ㆍ경보 발령",
            "국가기반체계보호관련 지역안전관리위원회 및 지역안전대책본부 구성ㆍ운영",
            "국가기반체계보호관련 인력ㆍ장비ㆍ물자 등의 동원명령",
            "국가기반체계보호관련 특별재난지역에 대한 지원 등",
            "국가기반체계보호관련 위험지구 설정",
            "국가기반체계보호관련 대피명령ㆍ강제대피조치ㆍ통행제한ㆍ응원ㆍ응급부담 등",
            "수상레저에 관한 사항",
            "구 통합방위협의회 운영",
            "하천관리(사용료, 기본자료조사, 수익자 부담금 징수 포함)",
            "하천공작물, 하천골재채취 허가",
            "하천공사의 조사, 측량, 설계",
            "지방하천 정비 기본계획 수립",
            "하천 편입토지 보상 및 폐천부지 관리",
            "안전정책 총괄ㆍ조정",
            "안전문화운동, 안전공동체 육성에 관한 사항",
            "안전지수, 안전지도에 관한 사항",
            "안전수준 진단ㆍ분석에 관한 사항",
            "승강기 제도 및 관리 업무",
            "원자력시설 인근 지역 주민보호 업무",
            "지역방사능 방재계획수립 시행",
            "방사능 방재대책본부 구성 및 운영",
            "방사능 방재훈련",
            "방사선비상계획구역 설정 관련 업무",
            "중대재해 예방에 관한 사항"
          ],
          "키워드_태그": [
            "재난_안전",
            "도시_건축",
            "행정_기획",
            "문화_교육"
          ],
          "children": []
        },
        {
          "id": "25040.안전도시국.건설과",
          "type": "과",
          "name": "건설과",
          "level": 2,
          "head_position": "건설과장",
          "head_grade": "",
          "정원": null,
          "근거조문": "시행규칙",
          "분장사무_원문": "제37조(건설과) 건설과장은 다음 사항을 분장한다.1. 건설행정의 종합 기획조정2. 건설공사용 자재 및 기구출납 보관3. 시설동원(일반토지, 건설업체, 중기정비업체)에 관한 사항4. 과적차량 단속5. 전문건설업 관리6. 가스(LP가스) 및 특정열 사용 기자재 시공업 등록7. 도로관리(철책유지 포함)8. 토목, 건설공사의 시행 및 지도9. 구가 시행하는 토목사업의 조사, 측량, 설계10. 도로안내표지판 설치 및 유지관리11. 사도개설ㆍ옹벽 및 공작물 축조허가12. 토지굴착에 대한 정리조치13. 도로굴착 및 도로공작물 제거ㆍ설치14. 지장전주 이설15. 지하수 관리(검침 및 사용료의 부과 징수)16. 하수도 계량기 설치 및 교체17. 하수종별 책정 및 변경18. 지하수 개발 및 지하수 수질검사19. 공공하수도 설치ㆍ개축ㆍ수선공사20. 공공하수도 정비 기본계획 수립21. 공공하수도의 점ㆍ사용료 부과징수22. 가로 및 공한지 정비23. 도로 점ㆍ사용료 부과징수24. 가로등, 보안등 관리25. 도로관련 생활민원 처리26. 도로상의 노점상, 노상적치물, 포장마차 등에 대한 지도ㆍ단속",
          "분장사무_항목": [
            "건설행정의 종합 기획조정",
            "건설공사용 자재 및 기구출납 보관",
            "시설동원(일반토지, 건설업체, 중기정비업체)에 관한 사항",
            "과적차량 단속",
            "전문건설업 관리",
            "가스(LP가스) 및 특정열 사용 기자재 시공업 등록",
            "도로관리(철책유지 포함)",
            "토목, 건설공사의 시행 및 지도",
            "구가 시행하는 토목사업의 조사, 측량, 설계",
            "도로안내표지판 설치 및 유지관리",
            "사도개설ㆍ옹벽 및 공작물 축조허가",
            "토지굴착에 대한 정리조치",
            "도로굴착 및 도로공작물 제거ㆍ설치",
            "지장전주 이설",
            "지하수 관리(검침 및 사용료의 부과 징수)",
            "하수도 계량기 설치 및 교체",
            "하수종별 책정 및 변경",
            "지하수 개발 및 지하수 수질검사",
            "공공하수도 설치ㆍ개축ㆍ수선공사",
            "공공하수도 정비 기본계획 수립",
            "공공하수도의 점ㆍ사용료 부과징수",
            "가로 및 공한지 정비",
            "도로 점ㆍ사용료 부과징수",
            "가로등, 보안등 관리",
            "도로관련 생활민원 처리",
            "도로상의 노점상, 노상적치물, 포장마차 등에 대한 지도ㆍ단속"
          ],
          "키워드_태그": [
            "환경",
            "교통",
            "도시_건축",
            "행정_기획"
          ],
          "children": []
        },
        {
          "id": "25040.안전도시국.건축과",
          "type": "과",
          "name": "건축과",
          "level": 2,
          "head_position": "건축과장",
          "head_grade": "",
          "정원": null,
          "근거조문": "시행규칙",
          "분장사무_원문": "제38조(건축과) 건축과장은 다음 사항을 분장한다.1. 건축의 허가, 시공, 준공처리 및 지도감독2. 위법 건축물 단속 및 조치3. 주택조합의 인ㆍ허가4. 주택자재 생산업체 지도ㆍ감독5. 건축사 지도감독6. 공작물 촉조 및 신고필증7. 증축등 변경신고 및 필증 교부8. 취락지역안의 건축신고9. 주택 철거ㆍ멸실 확인10. 소규모 건축신고에 관한 사항11. 100평방미터 미만 건축 허가에 관한 사항12. 건축물 사용승인에 관한 사항13. 건축물ㆍ공동주택 부설주차장 설치허가 및 관리14. 개발제한구역내 건축허가,시공,준공 처리 및 지도감독15. 학교용지 부담금 및 과태료 부과ㆍ징수에 관한 사항16. 건축물 대장 등ㆍ초본 교부 및 열람17. 건축물 대장의 작성, 전환, 합병, 정정, 말소, 변경업무18. 나대지상의 장애물(포장마차 등) 단속 및 정리19. 공공디자인 시범사업 기획 및 추진20. 공공디자인 공모사업21. 도시경관조례 제정 및 운영22. 도시경관종합계획 수립23. 도시디자인종합계획 수립24. 도시환경색채정립25. 경관사업 추진협의체 구성26. 옥외광고물 허가ㆍ신고 및 옥외광고물 안전도 검사27. 옥외광고업의 지도관리28. 옥외광고물의 사후관리",
          "분장사무_항목": [
            "건축의 허가, 시공, 준공처리 및 지도감독",
            "위법 건축물 단속 및 조치",
            "주택조합의 인ㆍ허가",
            "주택자재 생산업체 지도ㆍ감독",
            "건축사 지도감독",
            "공작물 촉조 및 신고필증",
            "증축등 변경신고 및 필증 교부",
            "취락지역안의 건축신고",
            "주택 철거ㆍ멸실 확인",
            "소규모 건축신고에 관한 사항",
            "100평방미터 미만 건축 허가에 관한 사항",
            "건축물 사용승인에 관한 사항",
            "건축물ㆍ공동주택 부설주차장 설치허가 및 관리",
            "개발제한구역내 건축허가,시공,준공 처리 및 지도감독",
            "학교용지 부담금 및 과태료 부과ㆍ징수에 관한 사항",
            "건축물 대장 등ㆍ초본 교부 및 열람",
            "건축물 대장의 작성, 전환, 합병, 정정, 말소, 변경업무",
            "나대지상의 장애물(포장마차 등) 단속 및 정리",
            "공공디자인 시범사업 기획 및 추진",
            "공공디자인 공모사업",
            "도시경관조례 제정 및 운영",
            "도시경관종합계획 수립",
            "도시디자인종합계획 수립",
            "도시환경색채정립",
            "경관사업 추진협의체 구성",
            "옥외광고물 허가ㆍ신고 및 옥외광고물 안전도 검사",
            "옥외광고업의 지도관리",
            "옥외광고물의 사후관리"
          ],
          "키워드_태그": [
            "환경",
            "교통",
            "복지",
            "재난_안전",
            "도시_건축",
            "경제_산업",
            "행정_기획"
          ],
          "children": []
        },
        {
          "id": "25040.안전도시국.공동주택과",
          "type": "과",
          "name": "공동주택과",
          "level": 2,
          "head_position": "공동주택과장",
          "head_grade": "",
          "정원": null,
          "근거조문": "시행규칙",
          "분장사무_원문": "제39조(공동주택과) 공동주택과장은 다음 사항을 분장한다.1. 공동주택관리에 관한 사항2. 주택관리업 등록 및 등록사항 변경에 관한 사항3. 주택임대관리업 등록 및 등록사항 변경에 관한 사항4. 공동주택관리 분쟁조정위원회 구성 및 운영에 관한 사항5. 임대주택관리에 관한 사항6. 주택임대사업자 등록 및 등록사항 변경에 관한 사항7. 공동주택관리 자문단 구성 및 운영에 관한 사항8. 공동주택 입주자대표회의 구성 및 관리규약에 관한 사항9. 공동주택 감사에 관한 사항10. 공동주택 교육에 관한 사항11. 공동주택 지원사업에 관한 사항12. 공동주택 모범관리단지 선정에 관한 사항13. 공동주택 어린이놀이시설 관리에 관한 사항14. 공동주택 불법구조변경 지도단속15.「건축법」에 의한 공동주택 건축 인ㆍ허가에 관한 사항16. 주택조합에 관한 사항17.「주택법」에 의한 공동주택 사업계획승인(허가) 및 입주자모집 및 사용검사에 관한 사항18.「공동주택관리법」에 의한 행위허가 및 신고에 관한 사항19.「공동주택관리법」에 의한 하자검사 업무20. 공동주택 분양가 심의위원회 구성 및 운영에 관한 사항21. 공동주택관리관련 민원처리 및 그 밖에 업무추진에 관한 사항",
          "분장사무_항목": [
            "공동주택관리에 관한 사항",
            "주택관리업 등록 및 등록사항 변경에 관한 사항",
            "주택임대관리업 등록 및 등록사항 변경에 관한 사항",
            "공동주택관리 분쟁조정위원회 구성 및 운영에 관한 사항",
            "임대주택관리에 관한 사항",
            "주택임대사업자 등록 및 등록사항 변경에 관한 사항",
            "공동주택관리 자문단 구성 및 운영에 관한 사항",
            "공동주택 입주자대표회의 구성 및 관리규약에 관한 사항",
            "공동주택 감사에 관한 사항",
            "공동주택 교육에 관한 사항",
            "공동주택 지원사업에 관한 사항",
            "공동주택 모범관리단지 선정에 관한 사항",
            "공동주택 어린이놀이시설 관리에 관한 사항",
            "공동주택 불법구조변경 지도단속15.「건축법」에 의한 공동주택 건축 인ㆍ허가에 관한 사항",
            "주택조합에 관한 사항17.「주택법」에 의한 공동주택 사업계획승인(허가) 및 입주자모집 및 사용검사에 관한 사항18.「공동주택관리법」에 의한 행위허가 및 신고에 관한 사항19.「공동주택관리법」에 의한 하자검사 업무",
            "공동주택 분양가 심의위원회 구성 및 운영에 관한 사항",
            "공동주택관리관련 민원처리 및 그 밖에 업무추진에 관한 사항"
          ],
          "키워드_태그": [
            "도시_건축",
            "행정_기획",
            "문화_교육"
          ],
          "children": []
        }
      ]
    }
  ],
  "validation": {
    "정원_합산_일치": null,
    "정원_총_조례기준": 933,
    "분장사무_누락_부서": [],
    "비고": []
  }
}