{
  "region": {
    "code": "31240",
    "name": "경기도 화성시",
    "level": "기초",
    "type": "시",
    "parent": "31"
  },
  "source": {
    "ordinance": {
      "name": "화성시 행정기구 및 정원 조례",
      "mst": "2048257",
      "last_amended": "20260201",
      "url": "https://www.law.go.kr/DRF/lawService.do?OC=open&target=ordin&MST=2048257&type=HTML",
      "fetched_at": "2026-05-09"
    },
    "enforcement_rule": {
      "name": "화성시 행정기구 및 정원 조례 시행규칙",
      "mst": "2063093",
      "last_amended": "20260201",
      "url": "https://www.law.go.kr/DRF/lawService.do?OC=open&target=ordin&MST=2063093&type=HTML",
      "fetched_at": "2026-05-09"
    },
    "staff_ordinance": {
      "name": "화성시 행정기구 및 정원 조례",
      "mst": "2048257",
      "last_amended": "20260201",
      "fetched_at": "2026-05-09"
    }
  },
  "totals": {
    "정원_총": 3382,
    "정원_근거조문": "화성시 행정기구 및 정원 조례 제2조",
    "정원_비고": ""
  },
  "structure": [
    {
      "id": "31240.공보실",
      "type": "실",
      "name": "공보실",
      "level": 1,
      "head_position": "공보실장",
      "head_grade": "",
      "정원": null,
      "근거조문": "조례 제6조",
      "분장사무_원문": "제6조(공보실에 두는 과)① 공보실에 언론담당관 및 홍보담당관을 둔다.② 공보실장은 다음 사무를 분장한다.1. 시정 홍보에 관한 사무2. 언론에 대한 보도계획 총괄 및 조정에 관한 사무3. 시정보도에 관한 사무4. 언론매체ㆍ언론브리핑에 관한 사무",
      "분장사무_항목": [
        "시정 홍보에 관한 사무",
        "언론에 대한 보도계획 총괄 및 조정에 관한 사무",
        "시정보도에 관한 사무",
        "언론매체ㆍ언론브리핑에 관한 사무"
      ],
      "키워드_태그": [],
      "children": [
        {
          "id": "31240.공보실.언론담당관",
          "type": "담당관",
          "name": "언론담당관",
          "level": 2,
          "head_position": "언론담당관",
          "head_grade": "",
          "정원": null,
          "근거조문": "조례",
          "분장사무_원문": "",
          "분장사무_항목": [],
          "키워드_태그": [],
          "children": []
        },
        {
          "id": "31240.공보실.홍보담당관",
          "type": "담당관",
          "name": "홍보담당관",
          "level": 2,
          "head_position": "홍보담당관",
          "head_grade": "",
          "정원": null,
          "근거조문": "조례",
          "분장사무_원문": "",
          "분장사무_항목": [],
          "키워드_태그": [],
          "children": []
        }
      ]
    },
    {
      "id": "31240.기획조정실",
      "type": "실",
      "name": "기획조정실",
      "level": 1,
      "head_position": "기획조정실장",
      "head_grade": "",
      "정원": null,
      "근거조문": "조례 제7조",
      "분장사무_원문": "제7조(기획조정실에 두는 과)① 기획조정실에 정책기획관ㆍ균형발전과ㆍ의회법무과ㆍ군공항대응과 및 정보통신과를 둔다.② 기획조정실장은 다음 사무를 분장한다.1. 시정의 종합기획 및 조정에 관한 사무2. 행정조직관리에 관한 사무3. 지방행정 혁신에 관한 사무4. 중요 전략사업 추진에 관한 사무5. 시 의회 협력 및 법제, 소송 및 규제개혁에 관한 사항6. 군공항 이전 대응 등에 관한 사무7. 행정전산 및 정보통신에 관한 사무",
      "분장사무_항목": [
        "시정의 종합기획 및 조정에 관한 사무",
        "행정조직관리에 관한 사무",
        "지방행정 혁신에 관한 사무",
        "중요 전략사업 추진에 관한 사무",
        "시 의회 협력 및 법제, 소송 및 규제개혁에 관한 사항",
        "군공항 이전 대응 등에 관한 사무",
        "행정전산 및 정보통신에 관한 사무"
      ],
      "키워드_태그": [
        "행정_기획"
      ],
      "children": [
        {
          "id": "31240.기획조정실.균형발전과",
          "type": "과",
          "name": "균형발전과",
          "level": 2,
          "head_position": "균형발전과장",
          "head_grade": "",
          "정원": null,
          "근거조문": "조례",
          "분장사무_원문": "",
          "분장사무_항목": [],
          "키워드_태그": [],
          "children": []
        },
        {
          "id": "31240.기획조정실.의회법무과",
          "type": "과",
          "name": "의회법무과",
          "level": 2,
          "head_position": "의회법무과장",
          "head_grade": "",
          "정원": null,
          "근거조문": "조례",
          "분장사무_원문": "",
          "분장사무_항목": [],
          "키워드_태그": [],
          "children": []
        },
        {
          "id": "31240.기획조정실.군공항대응과",
          "type": "과",
          "name": "군공항대응과",
          "level": 2,
          "head_position": "군공항대응과장",
          "head_grade": "",
          "정원": null,
          "근거조문": "조례",
          "분장사무_원문": "",
          "분장사무_항목": [],
          "키워드_태그": [],
          "children": []
        },
        {
          "id": "31240.기획조정실.정보통신과",
          "type": "과",
          "name": "정보통신과",
          "level": 2,
          "head_position": "정보통신과장",
          "head_grade": "",
          "정원": null,
          "근거조문": "조례",
          "분장사무_원문": "",
          "분장사무_항목": [],
          "키워드_태그": [],
          "children": []
        }
      ]
    },
    {
      "id": "31240.안전건설실",
      "type": "실",
      "name": "안전건설실",
      "level": 1,
      "head_position": "안전건설실장",
      "head_grade": "",
      "정원": null,
      "근거조문": "조례 제8조",
      "분장사무_원문": "제8조(안전건설실에 두는 과)① 안전건설실에 안전정책과ㆍ재난대응과ㆍ건설과 및 도로과를 둔다.② 안전건설실장은 다음 사무를 분장한다.1. 안전정책 총괄ㆍ조정, 안전점검, 중대재해 예방 및 민방위에 관한 사무2. 재난 총괄관리, 재난상황 유지ㆍ관리 및 재난 수습에 관한 사무3. 건설행정, 행정재산, 하천계획, 하천시설, 농어촌 기반 시설물에 관한 사무4. 도로계획, 도로건설, 민자도로 및 건설기술심의에 관한 사무5. 도로구조물, 도로정비, 보도 및 자전거도로에 관한 사무",
      "분장사무_항목": [
        "안전정책 총괄ㆍ조정, 안전점검, 중대재해 예방 및 민방위에 관한 사무",
        "재난 총괄관리, 재난상황 유지ㆍ관리 및 재난 수습에 관한 사무",
        "건설행정, 행정재산, 하천계획, 하천시설, 농어촌 기반 시설물에 관한 사무",
        "도로계획, 도로건설, 민자도로 및 건설기술심의에 관한 사무",
        "도로구조물, 도로정비, 보도 및 자전거도로에 관한 사무"
      ],
      "키워드_태그": [
        "교통",
        "재난_안전",
        "도시_건축"
      ],
      "children": [
        {
          "id": "31240.안전건설실.안전정책과",
          "type": "과",
          "name": "안전정책과",
          "level": 2,
          "head_position": "안전정책과장",
          "head_grade": "",
          "정원": null,
          "근거조문": "조례",
          "분장사무_원문": "",
          "분장사무_항목": [],
          "키워드_태그": [
            "재난_안전"
          ],
          "children": []
        },
        {
          "id": "31240.안전건설실.재난대응과",
          "type": "과",
          "name": "재난대응과",
          "level": 2,
          "head_position": "재난대응과장",
          "head_grade": "",
          "정원": null,
          "근거조문": "조례",
          "분장사무_원문": "",
          "분장사무_항목": [],
          "키워드_태그": [
            "재난_안전"
          ],
          "children": []
        },
        {
          "id": "31240.안전건설실.건설과",
          "type": "과",
          "name": "건설과",
          "level": 2,
          "head_position": "건설과장",
          "head_grade": "",
          "정원": null,
          "근거조문": "조례",
          "분장사무_원문": "",
          "분장사무_항목": [],
          "키워드_태그": [],
          "children": []
        },
        {
          "id": "31240.안전건설실.도로과",
          "type": "과",
          "name": "도로과",
          "level": 2,
          "head_position": "도로과장",
          "head_grade": "",
          "정원": null,
          "근거조문": "조례",
          "분장사무_원문": "",
          "분장사무_항목": [],
          "키워드_태그": [
            "교통"
          ],
          "children": []
        }
      ]
    },
    {
      "id": "31240.자치행정국",
      "type": "국",
      "name": "자치행정국",
      "level": 1,
      "head_position": "자치행정국장",
      "head_grade": "",
      "정원": null,
      "근거조문": "조례 제9조",
      "분장사무_원문": "제9조(자치행정국에 두는 과)① 자치행정국에 행정지원과ㆍ자치분권과ㆍ시민협력과ㆍ인사과ㆍ민원여권과 및 행정종합관찰관을 둔다.② 자치행정국장은 다음 사무를 분장한다.1. 총무, 의전, 직원복지, 국내ㆍ외 교류, 행정 조정 등에 관한 사무2. 공무원의 복무, 공무직 운영 및 공인ㆍ기록물관리 등에 관한 사항3. 하부행정기관의 지도ㆍ감독 등에 관한 사무4. 자치행정, 선거, 자치분권에 관한 사무5. 자원봉사, 주민자치, 마을공동체 및 민간협력에 관한 사무6. 인사, 채용, 공무원 교육훈련 및 성과관리 등에 관한 사무7. 민원행정, 민원조정, 여권, 콜센터 운영, 민원제도 개선에 관한 사무8. 행정종합관찰관 운영에 관한 사무",
      "분장사무_항목": [
        "총무, 의전, 직원복지, 국내ㆍ외 교류, 행정 조정 등에 관한 사무",
        "공무원의 복무, 공무직 운영 및 공인ㆍ기록물관리 등에 관한 사항",
        "하부행정기관의 지도ㆍ감독 등에 관한 사무",
        "자치행정, 선거, 자치분권에 관한 사무",
        "자원봉사, 주민자치, 마을공동체 및 민간협력에 관한 사무",
        "인사, 채용, 공무원 교육훈련 및 성과관리 등에 관한 사무",
        "민원행정, 민원조정, 여권, 콜센터 운영, 민원제도 개선에 관한 사무",
        "행정종합관찰관 운영에 관한 사무"
      ],
      "키워드_태그": [
        "복지",
        "행정_기획",
        "문화_교육"
      ],
      "children": [
        {
          "id": "31240.자치행정국.행정지원과",
          "type": "과",
          "name": "행정지원과",
          "level": 2,
          "head_position": "행정지원과장",
          "head_grade": "",
          "정원": null,
          "근거조문": "조례",
          "분장사무_원문": "",
          "분장사무_항목": [],
          "키워드_태그": [],
          "children": []
        },
        {
          "id": "31240.자치행정국.자치분권과",
          "type": "과",
          "name": "자치분권과",
          "level": 2,
          "head_position": "자치분권과장",
          "head_grade": "",
          "정원": null,
          "근거조문": "조례",
          "분장사무_원문": "",
          "분장사무_항목": [],
          "키워드_태그": [],
          "children": []
        },
        {
          "id": "31240.자치행정국.시민협력과",
          "type": "과",
          "name": "시민협력과",
          "level": 2,
          "head_position": "시민협력과장",
          "head_grade": "",
          "정원": null,
          "근거조문": "조례",
          "분장사무_원문": "",
          "분장사무_항목": [],
          "키워드_태그": [],
          "children": []
        },
        {
          "id": "31240.자치행정국.인사과",
          "type": "과",
          "name": "인사과",
          "level": 2,
          "head_position": "인사과장",
          "head_grade": "",
          "정원": null,
          "근거조문": "조례",
          "분장사무_원문": "",
          "분장사무_항목": [],
          "키워드_태그": [
            "행정_기획"
          ],
          "children": []
        },
        {
          "id": "31240.자치행정국.민원여권과",
          "type": "과",
          "name": "민원여권과",
          "level": 2,
          "head_position": "민원여권과장",
          "head_grade": "",
          "정원": null,
          "근거조문": "조례",
          "분장사무_원문": "",
          "분장사무_항목": [],
          "키워드_태그": [],
          "children": []
        }
      ]
    },
    {
      "id": "31240.재정국",
      "type": "국",
      "name": "재정국",
      "level": 1,
      "head_position": "재정국장",
      "head_grade": "",
      "정원": null,
      "근거조문": "조례 제10조",
      "분장사무_원문": "제10조(재정국에 두는 과)① 재정국에 예산재정과ㆍ세정과ㆍ징수과ㆍ회계과 및 재산관리과를 둔다.② 재정국장은 다음 사무를 분장한다.1. 예산 편성ㆍ집행ㆍ감독, 재정분석 및 국도비 확보에 관한 사무2. 지방세, 세입관리 및 세무조사에 관한 사무3. 지방세 및 세외수입의 체납징수에 관한 사무4. 지출, 급여, 재무회계, 계약, 물품관리, 자금관리 및 운용에 관한 사무5. 공유재산관리, 청사관리 및 공용차량에 관한 사무",
      "분장사무_항목": [
        "예산 편성ㆍ집행ㆍ감독, 재정분석 및 국도비 확보에 관한 사무",
        "지방세, 세입관리 및 세무조사에 관한 사무",
        "지방세 및 세외수입의 체납징수에 관한 사무",
        "지출, 급여, 재무회계, 계약, 물품관리, 자금관리 및 운용에 관한 사무",
        "공유재산관리, 청사관리 및 공용차량에 관한 사무"
      ],
      "키워드_태그": [
        "행정_기획"
      ],
      "children": [
        {
          "id": "31240.재정국.예산재정과",
          "type": "과",
          "name": "예산재정과",
          "level": 2,
          "head_position": "예산재정과장",
          "head_grade": "",
          "정원": null,
          "근거조문": "조례",
          "분장사무_원문": "",
          "분장사무_항목": [],
          "키워드_태그": [
            "행정_기획"
          ],
          "children": []
        },
        {
          "id": "31240.재정국.세정과",
          "type": "과",
          "name": "세정과",
          "level": 2,
          "head_position": "세정과장",
          "head_grade": "",
          "정원": null,
          "근거조문": "조례",
          "분장사무_원문": "",
          "분장사무_항목": [],
          "키워드_태그": [],
          "children": []
        },
        {
          "id": "31240.재정국.징수과",
          "type": "과",
          "name": "징수과",
          "level": 2,
          "head_position": "징수과장",
          "head_grade": "",
          "정원": null,
          "근거조문": "조례",
          "분장사무_원문": "",
          "분장사무_항목": [],
          "키워드_태그": [],
          "children": []
        },
        {
          "id": "31240.재정국.회계과",
          "type": "과",
          "name": "회계과",
          "level": 2,
          "head_position": "회계과장",
          "head_grade": "",
          "정원": null,
          "근거조문": "조례",
          "분장사무_원문": "",
          "분장사무_항목": [],
          "키워드_태그": [],
          "children": []
        },
        {
          "id": "31240.재정국.재산관리과",
          "type": "과",
          "name": "재산관리과",
          "level": 2,
          "head_position": "재산관리과장",
          "head_grade": "",
          "정원": null,
          "근거조문": "조례",
          "분장사무_원문": "",
          "분장사무_항목": [],
          "키워드_태그": [],
          "children": []
        }
      ]
    },
    {
      "id": "31240.돌봄복지국",
      "type": "국",
      "name": "돌봄복지국",
      "level": 1,
      "head_position": "돌봄복지국장",
      "head_grade": "",
      "정원": null,
      "근거조문": "조례 제11조",
      "분장사무_원문": "제11조(돌봄복지국에 두는 과)① 돌봄복지국에 복지정책과ㆍ통합돌봄과ㆍ장애인복지과ㆍ중장년노인과 및 위생정책과를 둔다.② 돌봄복지국장은 다음 사무를 분장한다.1. 지역복지계획 수립 등 주민복지에 관한 사무2. 통합돌봄 종합계획 수립 및 맞춤형 복지서비스 지원에 관한 사무3. 장애인 복지ㆍ돌봄에 관한 사무4. 중장년 정책수립 및 노인 복지ㆍ돌봄에 관한 사무5. 위생관리, 위생지도, 식품위생 및 장묘문화에 관한 사무",
      "분장사무_항목": [
        "지역복지계획 수립 등 주민복지에 관한 사무",
        "통합돌봄 종합계획 수립 및 맞춤형 복지서비스 지원에 관한 사무",
        "장애인 복지ㆍ돌봄에 관한 사무",
        "중장년 정책수립 및 노인 복지ㆍ돌봄에 관한 사무",
        "위생관리, 위생지도, 식품위생 및 장묘문화에 관한 사무"
      ],
      "키워드_태그": [
        "복지",
        "문화_교육",
        "보건_위생"
      ],
      "children": [
        {
          "id": "31240.돌봄복지국.복지정책과",
          "type": "과",
          "name": "복지정책과",
          "level": 2,
          "head_position": "복지정책과장",
          "head_grade": "",
          "정원": null,
          "근거조문": "조례",
          "분장사무_원문": "",
          "분장사무_항목": [],
          "키워드_태그": [
            "복지"
          ],
          "children": []
        },
        {
          "id": "31240.돌봄복지국.통합돌봄과",
          "type": "과",
          "name": "통합돌봄과",
          "level": 2,
          "head_position": "통합돌봄과장",
          "head_grade": "",
          "정원": null,
          "근거조문": "조례",
          "분장사무_원문": "",
          "분장사무_항목": [],
          "키워드_태그": [],
          "children": []
        },
        {
          "id": "31240.돌봄복지국.장애인복지과",
          "type": "과",
          "name": "장애인복지과",
          "level": 2,
          "head_position": "장애인복지과장",
          "head_grade": "",
          "정원": null,
          "근거조문": "조례",
          "분장사무_원문": "",
          "분장사무_항목": [],
          "키워드_태그": [
            "복지"
          ],
          "children": []
        },
        {
          "id": "31240.돌봄복지국.중장년노인과",
          "type": "과",
          "name": "중장년노인과",
          "level": 2,
          "head_position": "중장년노인과장",
          "head_grade": "",
          "정원": null,
          "근거조문": "조례",
          "분장사무_원문": "",
          "분장사무_항목": [],
          "키워드_태그": [
            "복지"
          ],
          "children": []
        },
        {
          "id": "31240.돌봄복지국.위생정책과",
          "type": "과",
          "name": "위생정책과",
          "level": 2,
          "head_position": "위생정책과장",
          "head_grade": "",
          "정원": null,
          "근거조문": "조례",
          "분장사무_원문": "",
          "분장사무_항목": [],
          "키워드_태그": [
            "보건_위생"
          ],
          "children": []
        }
      ]
    },
    {
      "id": "31240.성평등가족국",
      "type": "국",
      "name": "성평등가족국",
      "level": 1,
      "head_position": "성평등가족국장",
      "head_grade": "",
      "정원": null,
      "근거조문": "조례 제12조",
      "분장사무_원문": "제12조(성평등가족국에 두는 과)① 성평등가족국에 저출생대응과ㆍ영유아보육과ㆍ아동친화과ㆍ청년청소년과 및 이주민지원과를 둔다.② 성평등가족국장은 다음 사무를 분장한다.1. 여성정책 및 성평등에 관한 사무2. 인구정책, 저출생ㆍ고령사회, 건강가정, 1인가구에 관한 사무3. 영유아 보육에 관한 사무4. 아동복지, 아동보호ㆍ돌봄에 관한 사무5. 청소년ㆍ청년 정책 수립 및 지원에 관한 사무6. 이주민, 다문화, 외국인에 관한 사무",
      "분장사무_항목": [
        "여성정책 및 성평등에 관한 사무",
        "인구정책, 저출생ㆍ고령사회, 건강가정, 1인가구에 관한 사무",
        "영유아 보육에 관한 사무",
        "아동복지, 아동보호ㆍ돌봄에 관한 사무",
        "청소년ㆍ청년 정책 수립 및 지원에 관한 사무",
        "이주민, 다문화, 외국인에 관한 사무"
      ],
      "키워드_태그": [
        "복지",
        "문화_교육"
      ],
      "children": [
        {
          "id": "31240.성평등가족국.저출생대응과",
          "type": "과",
          "name": "저출생대응과",
          "level": 2,
          "head_position": "저출생대응과장",
          "head_grade": "",
          "정원": null,
          "근거조문": "조례",
          "분장사무_원문": "",
          "분장사무_항목": [],
          "키워드_태그": [],
          "children": []
        },
        {
          "id": "31240.성평등가족국.영유아보육과",
          "type": "과",
          "name": "영유아보육과",
          "level": 2,
          "head_position": "영유아보육과장",
          "head_grade": "",
          "정원": null,
          "근거조문": "조례",
          "분장사무_원문": "",
          "분장사무_항목": [],
          "키워드_태그": [],
          "children": []
        },
        {
          "id": "31240.성평등가족국.아동친화과",
          "type": "과",
          "name": "아동친화과",
          "level": 2,
          "head_position": "아동친화과장",
          "head_grade": "",
          "정원": null,
          "근거조문": "조례",
          "분장사무_원문": "",
          "분장사무_항목": [],
          "키워드_태그": [
            "복지"
          ],
          "children": []
        },
        {
          "id": "31240.성평등가족국.청년청소년과",
          "type": "과",
          "name": "청년청소년과",
          "level": 2,
          "head_position": "청년청소년과장",
          "head_grade": "",
          "정원": null,
          "근거조문": "조례",
          "분장사무_원문": "",
          "분장사무_항목": [],
          "키워드_태그": [
            "문화_교육"
          ],
          "children": []
        },
        {
          "id": "31240.성평등가족국.이주민지원과",
          "type": "과",
          "name": "이주민지원과",
          "level": 2,
          "head_position": "이주민지원과장",
          "head_grade": "",
          "정원": null,
          "근거조문": "조례",
          "분장사무_원문": "",
          "분장사무_항목": [],
          "키워드_태그": [],
          "children": []
        }
      ]
    },
    {
      "id": "31240.농정해양국",
      "type": "국",
      "name": "농정해양국",
      "level": 1,
      "head_position": "농정해양국장",
      "head_grade": "",
      "정원": null,
      "근거조문": "조례 제13조",
      "분장사무_원문": "제13조(농정해양국에 두는 과)① 농정해양국에 농업정책과ㆍ농식품유통과ㆍ축산정책과ㆍ동물보호과 및 해양수산과를 둔다.② 농정해양국장은 다음 사무를 분장한다.1. 농업정책, 농업지원, 농지관리 및 농업기반에 관한 사무2. 농산물 유통, 학교 및 공공급식에 관한 사무3. 축산정책, 축산행정, 가축방역 및 축산물유통에 관한 사무4. 반려동물문화, 동물보호 및 동물구조 등에 관한 사무5. 해양수산행정, 수산물유통 및 어업기반에 관한 사무",
      "분장사무_항목": [
        "농업정책, 농업지원, 농지관리 및 농업기반에 관한 사무",
        "농산물 유통, 학교 및 공공급식에 관한 사무",
        "축산정책, 축산행정, 가축방역 및 축산물유통에 관한 사무",
        "반려동물문화, 동물보호 및 동물구조 등에 관한 사무",
        "해양수산행정, 수산물유통 및 어업기반에 관한 사무"
      ],
      "키워드_태그": [
        "경제_산업",
        "문화_교육",
        "보건_위생"
      ],
      "children": [
        {
          "id": "31240.농정해양국.농업정책과",
          "type": "과",
          "name": "농업정책과",
          "level": 2,
          "head_position": "농업정책과장",
          "head_grade": "",
          "정원": null,
          "근거조문": "조례",
          "분장사무_원문": "",
          "분장사무_항목": [],
          "키워드_태그": [
            "경제_산업"
          ],
          "children": []
        },
        {
          "id": "31240.농정해양국.농식품유통과",
          "type": "과",
          "name": "농식품유통과",
          "level": 2,
          "head_position": "농식품유통과장",
          "head_grade": "",
          "정원": null,
          "근거조문": "조례",
          "분장사무_원문": "",
          "분장사무_항목": [],
          "키워드_태그": [],
          "children": []
        },
        {
          "id": "31240.농정해양국.축산정책과",
          "type": "과",
          "name": "축산정책과",
          "level": 2,
          "head_position": "축산정책과장",
          "head_grade": "",
          "정원": null,
          "근거조문": "조례",
          "분장사무_원문": "",
          "분장사무_항목": [],
          "키워드_태그": [],
          "children": []
        },
        {
          "id": "31240.농정해양국.동물보호과",
          "type": "과",
          "name": "동물보호과",
          "level": 2,
          "head_position": "동물보호과장",
          "head_grade": "",
          "정원": null,
          "근거조문": "조례",
          "분장사무_원문": "",
          "분장사무_항목": [],
          "키워드_태그": [],
          "children": []
        },
        {
          "id": "31240.농정해양국.해양수산과",
          "type": "과",
          "name": "해양수산과",
          "level": 2,
          "head_position": "해양수산과장",
          "head_grade": "",
          "정원": null,
          "근거조문": "조례",
          "분장사무_원문": "",
          "분장사무_항목": [],
          "키워드_태그": [],
          "children": []
        }
      ]
    },
    {
      "id": "31240.교통국",
      "type": "국",
      "name": "교통국",
      "level": 1,
      "head_position": "교통국장",
      "head_grade": "",
      "정원": null,
      "근거조문": "조례 제14조",
      "분장사무_원문": "제14조(교통국에 두는 과)① 교통국에 교통정책과ㆍ철도전략과ㆍ대중교통과ㆍ주차물류과 및 차량등록과를 둔다.② 교통국장은 다음 사무를 분장한다.1. 교통정책, 교통평가, 교통시설, 교통정보에 관한 사무2. 지능형교통체계 및 딥러닝 기반 교통관리시스템 구축 등 첨단교통체계 추진에 관한 사무3. 철도(광역, 일반) 추진에 관한 사무4. 대중교통정책 발굴 등 대중교통에 관한 사무5. 택시, 버스, 여객 운수, 자동차 관리에 관한 사무6. 주차시설, 공영주차장 조성 및 운영, 교통지도에 관한 사무7. 물류정책, 물류단지 및 화물운수에 관한 사무8. 차량등록 및 검사, 자동차 관리에 관한 사무9. 건설중기 등록사무 및 조종사 관리에 관한 사무",
      "분장사무_항목": [
        "교통정책, 교통평가, 교통시설, 교통정보에 관한 사무",
        "지능형교통체계 및 딥러닝 기반 교통관리시스템 구축 등 첨단교통체계 추진에 관한 사무",
        "철도(광역, 일반) 추진에 관한 사무",
        "대중교통정책 발굴 등 대중교통에 관한 사무",
        "택시, 버스, 여객 운수, 자동차 관리에 관한 사무",
        "주차시설, 공영주차장 조성 및 운영, 교통지도에 관한 사무",
        "물류정책, 물류단지 및 화물운수에 관한 사무",
        "차량등록 및 검사, 자동차 관리에 관한 사무",
        "건설중기 등록사무 및 조종사 관리에 관한 사무"
      ],
      "키워드_태그": [
        "교통"
      ],
      "children": [
        {
          "id": "31240.교통국.교통정책과",
          "type": "과",
          "name": "교통정책과",
          "level": 2,
          "head_position": "교통정책과장",
          "head_grade": "",
          "정원": null,
          "근거조문": "조례",
          "분장사무_원문": "",
          "분장사무_항목": [],
          "키워드_태그": [
            "교통"
          ],
          "children": []
        },
        {
          "id": "31240.교통국.철도전략과",
          "type": "과",
          "name": "철도전략과",
          "level": 2,
          "head_position": "철도전략과장",
          "head_grade": "",
          "정원": null,
          "근거조문": "조례",
          "분장사무_원문": "",
          "분장사무_항목": [],
          "키워드_태그": [],
          "children": []
        },
        {
          "id": "31240.교통국.대중교통과",
          "type": "과",
          "name": "대중교통과",
          "level": 2,
          "head_position": "대중교통과장",
          "head_grade": "",
          "정원": null,
          "근거조문": "조례",
          "분장사무_원문": "",
          "분장사무_항목": [],
          "키워드_태그": [
            "교통"
          ],
          "children": []
        },
        {
          "id": "31240.교통국.주차물류과",
          "type": "과",
          "name": "주차물류과",
          "level": 2,
          "head_position": "주차물류과장",
          "head_grade": "",
          "정원": null,
          "근거조문": "조례",
          "분장사무_원문": "",
          "분장사무_항목": [],
          "키워드_태그": [
            "교통"
          ],
          "children": []
        },
        {
          "id": "31240.교통국.차량등록과",
          "type": "과",
          "name": "차량등록과",
          "level": 2,
          "head_position": "차량등록과장",
          "head_grade": "",
          "정원": null,
          "근거조문": "조례",
          "분장사무_원문": "",
          "분장사무_항목": [],
          "키워드_태그": [],
          "children": []
        }
      ]
    },
    {
      "id": "31240.도시정책실",
      "type": "실",
      "name": "도시정책실",
      "level": 1,
      "head_position": "도시정책실장",
      "head_grade": "",
      "정원": null,
      "근거조문": "조례 제15조",
      "분장사무_원문": "제15조(도시정책실에 두는 과)① 도시정책실에 도시정책과ㆍ도시계획상임기획단ㆍ도시개발과ㆍ신도시조성과 및 토지정보과를 둔다.② 도시정책실장은 다음 사무를 분장한다.1. 국토 및 자연자원의 보존ㆍ이용에 관한 사무2. 도시계획ㆍ지구단위ㆍ도시정보화에 관한 사무3. 성장관리방안 수립에 관한 사무4. 도시계획ㆍ공동(도시ㆍ건축)위원회 및 경관위원회 운영에 관한 사무5. 공공디자인 및 도시경관에 관한 사무6. 도시계획ㆍ인허가에 대한 정책 조정에 관한 사무7. 도시개발 종합계획 수립ㆍ추진, 도시재생, 개발행위(농지ㆍ산지전용 포함) 등에 관한 사무8. 택지ㆍ도시개발 등 공영개발에 관한 사무9. 지적ㆍ토지ㆍ지가ㆍ개발부담금 및 도로명주소에 관한 사무",
      "분장사무_항목": [
        "국토 및 자연자원의 보존ㆍ이용에 관한 사무",
        "도시계획ㆍ지구단위ㆍ도시정보화에 관한 사무",
        "성장관리방안 수립에 관한 사무",
        "도시계획ㆍ공동(도시ㆍ건축)위원회 및 경관위원회 운영에 관한 사무",
        "공공디자인 및 도시경관에 관한 사무",
        "도시계획ㆍ인허가에 대한 정책 조정에 관한 사무",
        "도시개발 종합계획 수립ㆍ추진, 도시재생, 개발행위(농지ㆍ산지전용 포함) 등에 관한 사무",
        "택지ㆍ도시개발 등 공영개발에 관한 사무",
        "지적ㆍ토지ㆍ지가ㆍ개발부담금 및 도로명주소에 관한 사무"
      ],
      "키워드_태그": [
        "교통",
        "도시_건축",
        "행정_기획"
      ],
      "children": [
        {
          "id": "31240.도시정책실.도시정책과",
          "type": "과",
          "name": "도시정책과",
          "level": 2,
          "head_position": "도시정책과장",
          "head_grade": "",
          "정원": null,
          "근거조문": "조례",
          "분장사무_원문": "",
          "분장사무_항목": [],
          "키워드_태그": [
            "도시_건축"
          ],
          "children": []
        },
        {
          "id": "31240.도시정책실.도시계획상임기획단",
          "type": "과",
          "name": "도시계획상임기획단",
          "level": 2,
          "head_position": "도시계획상임기획단장",
          "head_grade": "",
          "정원": null,
          "근거조문": "조례",
          "분장사무_원문": "",
          "분장사무_항목": [],
          "키워드_태그": [
            "도시_건축",
            "행정_기획"
          ],
          "children": []
        },
        {
          "id": "31240.도시정책실.도시개발과",
          "type": "과",
          "name": "도시개발과",
          "level": 2,
          "head_position": "도시개발과장",
          "head_grade": "",
          "정원": null,
          "근거조문": "조례",
          "분장사무_원문": "",
          "분장사무_항목": [],
          "키워드_태그": [
            "도시_건축"
          ],
          "children": []
        },
        {
          "id": "31240.도시정책실.신도시조성과",
          "type": "과",
          "name": "신도시조성과",
          "level": 2,
          "head_position": "신도시조성과장",
          "head_grade": "",
          "정원": null,
          "근거조문": "조례",
          "분장사무_원문": "",
          "분장사무_항목": [],
          "키워드_태그": [
            "도시_건축"
          ],
          "children": []
        },
        {
          "id": "31240.도시정책실.토지정보과",
          "type": "과",
          "name": "토지정보과",
          "level": 2,
          "head_position": "토지정보과장",
          "head_grade": "",
          "정원": null,
          "근거조문": "조례",
          "분장사무_원문": "",
          "분장사무_항목": [],
          "키워드_태그": [],
          "children": []
        }
      ]
    },
    {
      "id": "31240.기업투자실",
      "type": "실",
      "name": "기업투자실",
      "level": 1,
      "head_position": "기업투자실장",
      "head_grade": "",
      "정원": null,
      "근거조문": "조례 제16조",
      "분장사무_원문": "제16조(기업투자실에 두는 과)① 기업투자실에 첨단산업과ㆍ기업지원과ㆍ투자유치과ㆍ지역경제과 및 노사협력과를 둔다.② 기업투자실장은 다음 사무를 분장한다.1. 기업ㆍ산업육성 정책수립 및 지원에 관한 사무2. 첨단산업 육성에 관한 사항3. 기업 지원, 통상 및 무역진흥, 공장설립에 관한 사무4. 산업단지 조성ㆍ지원 및 국내ㆍ외 기업 투자유치에 관한 사항5. 지역경제정책, 전통시장 등 소상공인 지원, 소비자유통에 관한 사무6. 일자리정책, 일자리창출, 노사협력 및 지원, 산업안전에 관한 사무7. 근로자종합복지관 위탁 운영에 관한 사항",
      "분장사무_항목": [
        "기업ㆍ산업육성 정책수립 및 지원에 관한 사무",
        "첨단산업 육성에 관한 사항",
        "기업 지원, 통상 및 무역진흥, 공장설립에 관한 사무",
        "산업단지 조성ㆍ지원 및 국내ㆍ외 기업 투자유치에 관한 사항",
        "지역경제정책, 전통시장 등 소상공인 지원, 소비자유통에 관한 사무",
        "일자리정책, 일자리창출, 노사협력 및 지원, 산업안전에 관한 사무",
        "근로자종합복지관 위탁 운영에 관한 사항"
      ],
      "키워드_태그": [
        "복지",
        "재난_안전",
        "경제_산업"
      ],
      "children": [
        {
          "id": "31240.기업투자실.첨단산업과",
          "type": "과",
          "name": "첨단산업과",
          "level": 2,
          "head_position": "첨단산업과장",
          "head_grade": "",
          "정원": null,
          "근거조문": "조례",
          "분장사무_원문": "",
          "분장사무_항목": [],
          "키워드_태그": [
            "경제_산업"
          ],
          "children": []
        },
        {
          "id": "31240.기업투자실.기업지원과",
          "type": "과",
          "name": "기업지원과",
          "level": 2,
          "head_position": "기업지원과장",
          "head_grade": "",
          "정원": null,
          "근거조문": "조례",
          "분장사무_원문": "",
          "분장사무_항목": [],
          "키워드_태그": [],
          "children": []
        },
        {
          "id": "31240.기업투자실.투자유치과",
          "type": "과",
          "name": "투자유치과",
          "level": 2,
          "head_position": "투자유치과장",
          "head_grade": "",
          "정원": null,
          "근거조문": "조례",
          "분장사무_원문": "",
          "분장사무_항목": [],
          "키워드_태그": [],
          "children": []
        },
        {
          "id": "31240.기업투자실.지역경제과",
          "type": "과",
          "name": "지역경제과",
          "level": 2,
          "head_position": "지역경제과장",
          "head_grade": "",
          "정원": null,
          "근거조문": "조례",
          "분장사무_원문": "",
          "분장사무_항목": [],
          "키워드_태그": [
            "경제_산업"
          ],
          "children": []
        },
        {
          "id": "31240.기업투자실.노사협력과",
          "type": "과",
          "name": "노사협력과",
          "level": 2,
          "head_position": "노사협력과장",
          "head_grade": "",
          "정원": null,
          "근거조문": "조례",
          "분장사무_원문": "",
          "분장사무_항목": [],
          "키워드_태그": [],
          "children": []
        }
      ]
    },
    {
      "id": "31240.문화관광국",
      "type": "국",
      "name": "문화관광국",
      "level": 1,
      "head_position": "문화관광국장",
      "head_grade": "",
      "정원": null,
      "근거조문": "조례 제17조",
      "분장사무_원문": "제17조(문화관광국에 두는 과)① 문화관광국에 문화예술과ㆍ문화유산과ㆍ독립기념관 및 관광진흥과를 둔다.② 문화관광국장은 다음 사무를 분장한다.1. 문화ㆍ예술에 관한 사항2. 문화시설 설치 및 운영에 관한 사항3. 문화유산 보존 및 관리에 관한 사항4. 화성시 독립운동기념관 운영ㆍ관리에 관한 사항5. 관광에 관한 사항",
      "분장사무_항목": [
        "문화ㆍ예술에 관한 사항",
        "문화시설 설치 및 운영에 관한 사항",
        "문화유산 보존 및 관리에 관한 사항",
        "화성시 독립운동기념관 운영ㆍ관리에 관한 사항",
        "관광에 관한 사항"
      ],
      "키워드_태그": [
        "경제_산업",
        "문화_교육"
      ],
      "children": [
        {
          "id": "31240.문화관광국.문화예술과",
          "type": "과",
          "name": "문화예술과",
          "level": 2,
          "head_position": "문화예술과장",
          "head_grade": "",
          "정원": null,
          "근거조문": "조례",
          "분장사무_원문": "",
          "분장사무_항목": [],
          "키워드_태그": [
            "문화_교육"
          ],
          "children": []
        },
        {
          "id": "31240.문화관광국.문화유산과",
          "type": "과",
          "name": "문화유산과",
          "level": 2,
          "head_position": "문화유산과장",
          "head_grade": "",
          "정원": null,
          "근거조문": "조례",
          "분장사무_원문": "",
          "분장사무_항목": [],
          "키워드_태그": [
            "문화_교육"
          ],
          "children": []
        },
        {
          "id": "31240.문화관광국.관광진흥과",
          "type": "과",
          "name": "관광진흥과",
          "level": 2,
          "head_position": "관광진흥과장",
          "head_grade": "",
          "정원": null,
          "근거조문": "조례",
          "분장사무_원문": "",
          "분장사무_항목": [],
          "키워드_태그": [
            "경제_산업"
          ],
          "children": []
        }
      ]
    },
    {
      "id": "31240.교육체육국",
      "type": "국",
      "name": "교육체육국",
      "level": 1,
      "head_position": "교육체육국장",
      "head_grade": "",
      "정원": null,
      "근거조문": "조례 제18조",
      "분장사무_원문": "제18조(교육체육국에 두는 과)① 교육체육국에 교육지원과ㆍ평생학습과ㆍ도서관정책과ㆍ체육진흥과 및 전국체전추진단을 둔다.② 교육체육국장은 다음 사무를 분장한다.1. 교육지원에 관한 사항2. 평생교육 진흥에 관한 사항3. 시립도서관 정책 수립ㆍ건립ㆍ운영ㆍ지원에 관한 사항4. 국민 체육진흥에 관한 사항5. 체육시설 설치 및 운영에 관한 사항6. 전국체육대회 개최에 관한 사항",
      "분장사무_항목": [
        "교육지원에 관한 사항",
        "평생교육 진흥에 관한 사항",
        "시립도서관 정책 수립ㆍ건립ㆍ운영ㆍ지원에 관한 사항",
        "국민 체육진흥에 관한 사항",
        "체육시설 설치 및 운영에 관한 사항",
        "전국체육대회 개최에 관한 사항"
      ],
      "키워드_태그": [
        "문화_교육"
      ],
      "children": [
        {
          "id": "31240.교육체육국.교육지원과",
          "type": "과",
          "name": "교육지원과",
          "level": 2,
          "head_position": "교육지원과장",
          "head_grade": "",
          "정원": null,
          "근거조문": "조례",
          "분장사무_원문": "",
          "분장사무_항목": [],
          "키워드_태그": [
            "문화_교육"
          ],
          "children": []
        },
        {
          "id": "31240.교육체육국.평생학습과",
          "type": "과",
          "name": "평생학습과",
          "level": 2,
          "head_position": "평생학습과장",
          "head_grade": "",
          "정원": null,
          "근거조문": "조례",
          "분장사무_원문": "",
          "분장사무_항목": [],
          "키워드_태그": [],
          "children": []
        },
        {
          "id": "31240.교육체육국.도서관정책과",
          "type": "과",
          "name": "도서관정책과",
          "level": 2,
          "head_position": "도서관정책과장",
          "head_grade": "",
          "정원": null,
          "근거조문": "조례",
          "분장사무_원문": "",
          "분장사무_항목": [],
          "키워드_태그": [
            "문화_교육"
          ],
          "children": []
        },
        {
          "id": "31240.교육체육국.체육진흥과",
          "type": "과",
          "name": "체육진흥과",
          "level": 2,
          "head_position": "체육진흥과장",
          "head_grade": "",
          "정원": null,
          "근거조문": "조례",
          "분장사무_원문": "",
          "분장사무_항목": [],
          "키워드_태그": [
            "문화_교육"
          ],
          "children": []
        },
        {
          "id": "31240.교육체육국.전국체전추진단",
          "type": "과",
          "name": "전국체전추진단",
          "level": 2,
          "head_position": "전국체전추진단장",
          "head_grade": "",
          "정원": null,
          "근거조문": "조례",
          "분장사무_원문": "",
          "분장사무_항목": [],
          "키워드_태그": [],
          "children": []
        }
      ]
    },
    {
      "id": "31240.주택국",
      "type": "국",
      "name": "주택국",
      "level": 1,
      "head_position": "주택국장",
      "head_grade": "",
      "정원": null,
      "근거조문": "조례 제19조",
      "분장사무_원문": "제19조(주택국에 두는 과)① 주택국에 주택정책과ㆍ공동주택과ㆍ건축과 및 공공건축과를 둔다.② 주택국장은 다음 사무를 분장한다.1. 주택정책 수립ㆍ추진 및 주거복지에 관한 사무2. 「도시 및 주거환경정비법」 추진에 관한 사무3. 공동주택, 주택관리 및 주택감사에 관한 사무4. 주택, 건축 및 주거환경 개선에 관한 사항5. 건축물 허가ㆍ관리, 건축지도, 건축안전 및 광고물에 관한 사무6. 공공시설(청사 포함)의 건립계획 및 공사에 관한 사무",
      "분장사무_항목": [
        "주택정책 수립ㆍ추진 및 주거복지에 관한 사무",
        "「도시 및 주거환경정비법」 추진에 관한 사무",
        "공동주택, 주택관리 및 주택감사에 관한 사무",
        "주택, 건축 및 주거환경 개선에 관한 사항",
        "건축물 허가ㆍ관리, 건축지도, 건축안전 및 광고물에 관한 사무",
        "공공시설(청사 포함)의 건립계획 및 공사에 관한 사무"
      ],
      "키워드_태그": [
        "환경",
        "복지",
        "재난_안전",
        "도시_건축",
        "행정_기획"
      ],
      "children": [
        {
          "id": "31240.주택국.주택정책과",
          "type": "과",
          "name": "주택정책과",
          "level": 2,
          "head_position": "주택정책과장",
          "head_grade": "",
          "정원": null,
          "근거조문": "조례",
          "분장사무_원문": "",
          "분장사무_항목": [],
          "키워드_태그": [
            "도시_건축"
          ],
          "children": []
        },
        {
          "id": "31240.주택국.공동주택과",
          "type": "과",
          "name": "공동주택과",
          "level": 2,
          "head_position": "공동주택과장",
          "head_grade": "",
          "정원": null,
          "근거조문": "조례",
          "분장사무_원문": "",
          "분장사무_항목": [],
          "키워드_태그": [
            "도시_건축"
          ],
          "children": []
        },
        {
          "id": "31240.주택국.건축과",
          "type": "과",
          "name": "건축과",
          "level": 2,
          "head_position": "건축과장",
          "head_grade": "",
          "정원": null,
          "근거조문": "조례",
          "분장사무_원문": "",
          "분장사무_항목": [],
          "키워드_태그": [
            "도시_건축"
          ],
          "children": []
        },
        {
          "id": "31240.주택국.공공건축과",
          "type": "과",
          "name": "공공건축과",
          "level": 2,
          "head_position": "공공건축과장",
          "head_grade": "",
          "정원": null,
          "근거조문": "조례",
          "분장사무_원문": "",
          "분장사무_항목": [],
          "키워드_태그": [
            "도시_건축"
          ],
          "children": []
        }
      ]
    },
    {
      "id": "31240.기후에너지환경국",
      "type": "국",
      "name": "기후에너지환경국",
      "level": 1,
      "head_position": "기후에너지환경국장",
      "head_grade": "",
      "정원": null,
      "근거조문": "조례 제20조",
      "분장사무_원문": "제20조(기후에너지환경국에 두는 과)① 기후에너지환경국에 기후환경정책과ㆍ신재생에너지과ㆍ물환경생태과ㆍ자원순환과 및 환경지도과를 둔다.② 기후에너지환경국장은 다음 사무를 분장한다.1. 환경행정ㆍ대기ㆍ수질관리의 총괄 관리에 관한 사무2. 에너지자원 및 신재생에너지 등 에너지 관리에 관한 사무3. 청소ㆍ자원재활용ㆍ음식물쓰레기ㆍ대형폐기물ㆍ쓰레기매립장ㆍ적환장 및 폐기물 종합처리에 관한 사무4. 환경오염사고 방제 및 행정조치에 관한 사무",
      "분장사무_항목": [
        "환경행정ㆍ대기ㆍ수질관리의 총괄 관리에 관한 사무",
        "에너지자원 및 신재생에너지 등 에너지 관리에 관한 사무",
        "청소ㆍ자원재활용ㆍ음식물쓰레기ㆍ대형폐기물ㆍ쓰레기매립장ㆍ적환장 및 폐기물 종합처리에 관한 사무",
        "환경오염사고 방제 및 행정조치에 관한 사무"
      ],
      "키워드_태그": [
        "기후",
        "환경",
        "에너지",
        "녹지_생태"
      ],
      "children": [
        {
          "id": "31240.기후에너지환경국.기후환경정책과",
          "type": "과",
          "name": "기후환경정책과",
          "level": 2,
          "head_position": "기후환경정책과장",
          "head_grade": "",
          "정원": null,
          "근거조문": "조례",
          "분장사무_원문": "",
          "분장사무_항목": [],
          "키워드_태그": [
            "기후",
            "환경"
          ],
          "children": []
        },
        {
          "id": "31240.기후에너지환경국.신재생에너지과",
          "type": "과",
          "name": "신재생에너지과",
          "level": 2,
          "head_position": "신재생에너지과장",
          "head_grade": "",
          "정원": null,
          "근거조문": "조례",
          "분장사무_원문": "",
          "분장사무_항목": [],
          "키워드_태그": [
            "에너지"
          ],
          "children": []
        },
        {
          "id": "31240.기후에너지환경국.물환경생태과",
          "type": "과",
          "name": "물환경생태과",
          "level": 2,
          "head_position": "물환경생태과장",
          "head_grade": "",
          "정원": null,
          "근거조문": "조례",
          "분장사무_원문": "",
          "분장사무_항목": [],
          "키워드_태그": [
            "환경",
            "녹지_생태"
          ],
          "children": []
        },
        {
          "id": "31240.기후에너지환경국.자원순환과",
          "type": "과",
          "name": "자원순환과",
          "level": 2,
          "head_position": "자원순환과장",
          "head_grade": "",
          "정원": null,
          "근거조문": "조례",
          "분장사무_원문": "",
          "분장사무_항목": [],
          "키워드_태그": [
            "환경"
          ],
          "children": []
        },
        {
          "id": "31240.기후에너지환경국.환경지도과",
          "type": "과",
          "name": "환경지도과",
          "level": 2,
          "head_position": "환경지도과장",
          "head_grade": "",
          "정원": null,
          "근거조문": "조례",
          "분장사무_원문": "",
          "분장사무_항목": [],
          "키워드_태그": [
            "환경"
          ],
          "children": []
        }
      ]
    },
    {
      "id": "31240.보좌기관",
      "type": "보좌기관",
      "name": "보좌기관",
      "level": 1,
      "head_position": "보좌기관",
      "head_grade": "",
      "정원": null,
      "근거조문": "조례 제5조",
      "분장사무_원문": "",
      "분장사무_항목": [],
      "키워드_태그": [],
      "children": [
        {
          "id": "31240.보좌기관.감사관",
          "type": "관",
          "name": "감사관",
          "level": 2,
          "head_position": "감사관장",
          "head_grade": "",
          "정원": null,
          "근거조문": "조례",
          "분장사무_원문": "",
          "분장사무_항목": [],
          "키워드_태그": [
            "행정_기획"
          ],
          "children": []
        },
        {
          "id": "31240.보좌기관.트램건설추진단",
          "type": "단",
          "name": "트램건설추진단",
          "level": 2,
          "head_position": "트램건설추진단장",
          "head_grade": "",
          "정원": null,
          "근거조문": "조례",
          "분장사무_원문": "",
          "분장사무_항목": [],
          "키워드_태그": [],
          "children": []
        },
        {
          "id": "31240.보좌기관.기본사회담당관",
          "type": "담당관",
          "name": "기본사회담당관",
          "level": 2,
          "head_position": "기본사회담당관",
          "head_grade": "",
          "정원": null,
          "근거조문": "조례",
          "분장사무_원문": "",
          "분장사무_항목": [],
          "키워드_태그": [],
          "children": []
        }
      ]
    },
    {
      "id": "31240.직속기관.보건소ㆍ보건지소ㆍ보건진료소",
      "type": "직속기관",
      "name": "보건소ㆍ보건지소ㆍ보건진료소",
      "level": 1,
      "head_position": "보건소ㆍ보건지소ㆍ보건진료소장",
      "head_grade": "",
      "정원": null,
      "근거조문": "조례 제21조",
      "분장사무_원문": "",
      "분장사무_항목": [],
      "키워드_태그": [
        "보건_위생"
      ],
      "children": []
    },
    {
      "id": "31240.직속기관.농업기술센터",
      "type": "직속기관",
      "name": "농업기술센터",
      "level": 1,
      "head_position": "농업기술센터장",
      "head_grade": "",
      "정원": null,
      "근거조문": "조례 제24조",
      "분장사무_원문": "",
      "분장사무_항목": [],
      "키워드_태그": [
        "경제_산업",
        "문화_교육"
      ],
      "children": []
    },
    {
      "id": "31240.사업소.사업소",
      "type": "사업소",
      "name": "사업소",
      "level": 1,
      "head_position": "사업소장",
      "head_grade": "",
      "정원": null,
      "근거조문": "조례 제27조",
      "분장사무_원문": "제30조(소관사무) 사업소별 소장이 관장하는 사무는 다음 각 호와 같다.1. 맑은물사업소가. 상수 종합계획 수립 및 조정ㆍ통제에 관한 사무나. 공기업 특별회계 예산편성 및 결산에 관한 사무다. 상수시설 설치 및 유지관리에 관한 사무라. 요금, 시설분담금, 급수장치손표, 제수수료의 부과ㆍ징수에 관한 사무마. 지하수 관리에 관한 사무바. 하수행정ㆍ하수처리시설 관리ㆍ하수관망 정비ㆍ우수에 관한 사무사. 그 밖에 사업소 운영관리에 관한 사무2. 공원녹지사업소가. 공원조성, 공원문화, 조경에 관한 사무나. 공원관리 및 운영에 관한 사무다. 산림조성, 산림보호, 산림휴양 및 녹지에 관한 사무라. 식물원 조성 및 관리에 관한 사무마. 보타닉가든 조성 및 운영에 관한 사무바. 그 밖에 사업소 운영ㆍ관리에 관한 사무3. 대외협력사무소가. 국회 및 정부 각 부처와의 대외 협력에 관한 사무나. 정부예산 확보 지원 활동 및 수익증대사업 발굴다. 그 밖에 사무소 운영ㆍ관리에 관한 사무",
      "분장사무_항목": [
        "맑은물사업소",
        "상수 종합계획 수립 및 조정ㆍ통제에 관한 사무",
        "공기업 특별회계 예산편성 및 결산에 관한 사무",
        "상수시설 설치 및 유지관리에 관한 사무",
        "요금, 시설분담금, 급수장치손표, 제수수료의 부과ㆍ징수에 관한 사무",
        "지하수 관리에 관한 사무",
        "하수행정ㆍ하수처리시설 관리ㆍ하수관망 정비ㆍ우수에 관한 사무",
        "그 밖에 사업소 운영관리에 관한 사무",
        "공원녹지사업소",
        "공원조성, 공원문화, 조경에 관한 사무",
        "공원관리 및 운영에 관한 사무",
        "산림조성, 산림보호, 산림휴양 및 녹지에 관한 사무",
        "식물원 조성 및 관리에 관한 사무",
        "보타닉가든 조성 및 운영에 관한 사무",
        "그 밖에 사업소 운영ㆍ관리에 관한 사무",
        "대외협력사무소",
        "국회 및 정부 각 부처와의 대외 협력에 관한 사무",
        "정부예산 확보 지원 활동 및 수익증대사업 발굴",
        "그 밖에 사무소 운영ㆍ관리에 관한 사무"
      ],
      "키워드_태그": [
        "녹지_생태",
        "도시_건축",
        "행정_기획",
        "문화_교육"
      ],
      "children": []
    }
  ],
  "validation": {
    "정원_합산_일치": null,
    "정원_총_조례기준": 3382,
    "분장사무_누락_부서": [
      "보좌기관"
    ],
    "비고": []
  }
}