{
  "region": {
    "code": "33730",
    "name": "충청북도 영동군",
    "level": "기초",
    "type": "군",
    "parent": "33"
  },
  "source": {
    "ordinance": {
      "name": "영동군 행정기구 설치 조례",
      "mst": "1924401",
      "last_amended": "20240507",
      "url": "https://www.law.go.kr/DRF/lawService.do?OC=open&target=ordin&MST=1924401&type=HTML",
      "fetched_at": "2026-05-09"
    },
    "enforcement_rule": {
      "name": "영동군 행정기구 설치 조례 시행규칙",
      "mst": "2090279",
      "last_amended": "20251205",
      "url": "https://www.law.go.kr/DRF/lawService.do?OC=open&target=ordin&MST=2090279&type=HTML",
      "fetched_at": "2026-05-09"
    },
    "staff_ordinance": {
      "name": "영동군 지방공무원 정원 조례",
      "mst": "2126725",
      "last_amended": "20260430",
      "fetched_at": "2026-05-09"
    }
  },
  "totals": {
    "정원_총": 743,
    "정원_근거조문": "영동군 지방공무원 정원 조례 제2조",
    "정원_비고": ""
  },
  "structure": [
    {
      "id": "33730.미래기획실",
      "type": "실",
      "name": "미래기획실",
      "level": 1,
      "head_position": "미래기획실장",
      "head_grade": "5급",
      "정원": null,
      "근거조문": "조례 제4조",
      "분장사무_원문": "제4조(미래기획실)① 미래기획실에 기획감사과, 미래전략과, 경제과, 농촌신활력과를 둔다.② 미래기획실의 분장사무에 관한 사항은 규칙으로 정한다. [전문개정 2023. 5. 3.]",
      "분장사무_항목": [
        "미래기획실에 기획감사과, 미래전략과, 경제과, 농촌신활력과를 둔다.",
        "미래기획실의 분장사무에 관한 사항은 규칙으로 정한",
        "[전문개정"
      ],
      "키워드_태그": [
        "경제_산업",
        "행정_기획"
      ],
      "children": [
        {
          "id": "33730.미래기획실.기획감사과",
          "type": "과",
          "name": "기획감사과",
          "level": 2,
          "head_position": "기획감사과장",
          "head_grade": "",
          "정원": null,
          "근거조문": "시행규칙",
          "분장사무_원문": "",
          "분장사무_항목": [],
          "키워드_태그": [
            "행정_기획"
          ],
          "children": []
        },
        {
          "id": "33730.미래기획실.미래전략과",
          "type": "과",
          "name": "미래전략과",
          "level": 2,
          "head_position": "미래전략과장",
          "head_grade": "",
          "정원": null,
          "근거조문": "시행규칙",
          "분장사무_원문": "",
          "분장사무_항목": [],
          "키워드_태그": [],
          "children": []
        },
        {
          "id": "33730.미래기획실.경제과",
          "type": "과",
          "name": "경제과",
          "level": 2,
          "head_position": "경제과장",
          "head_grade": "",
          "정원": null,
          "근거조문": "시행규칙",
          "분장사무_원문": "",
          "분장사무_항목": [],
          "키워드_태그": [
            "경제_산업"
          ],
          "children": []
        },
        {
          "id": "33730.미래기획실.농촌신활력과",
          "type": "과",
          "name": "농촌신활력과",
          "level": 2,
          "head_position": "농촌신활력과장",
          "head_grade": "",
          "정원": null,
          "근거조문": "시행규칙",
          "분장사무_원문": "",
          "분장사무_항목": [],
          "키워드_태그": [],
          "children": []
        }
      ]
    },
    {
      "id": "33730.행정관광복지국",
      "type": "국",
      "name": "행정관광복지국",
      "level": 1,
      "head_position": "행정관광복지국장",
      "head_grade": "5급",
      "정원": null,
      "근거조문": "조례 제5조",
      "분장사무_원문": "제5조(행정관광복지국)① 행정관광복지국에 행정과, 관광과, 국악문화예술과, 주민복지과, 가족행복과, 민원과, 재무과를 둔다. <개정 18.11.5, 2023.5.3.>② 행정관광복지국의 분장사무에 관한 사항은 규칙으로 정한다. <개정 2023. 5. 3.> [제목개정 2023. 5. 3.]",
      "분장사무_항목": [
        "행정관광복지국에 행정과, 관광과, 국악문화예술과, 주민복지과, 가족행복과, 민원과, 재무과를 둔",
        "행정관광복지국의 분장사무에 관한 사항은 규칙으로 정한",
        "[제목개정"
      ],
      "키워드_태그": [
        "복지",
        "경제_산업",
        "문화_교육"
      ],
      "children": [
        {
          "id": "33730.행정관광복지국.행정과",
          "type": "과",
          "name": "행정과",
          "level": 2,
          "head_position": "행정과장",
          "head_grade": "",
          "정원": null,
          "근거조문": "시행규칙",
          "분장사무_원문": "",
          "분장사무_항목": [],
          "키워드_태그": [],
          "children": []
        },
        {
          "id": "33730.행정관광복지국.관광과",
          "type": "과",
          "name": "관광과",
          "level": 2,
          "head_position": "관광과장",
          "head_grade": "",
          "정원": null,
          "근거조문": "시행규칙",
          "분장사무_원문": "",
          "분장사무_항목": [],
          "키워드_태그": [
            "경제_산업"
          ],
          "children": []
        },
        {
          "id": "33730.행정관광복지국.국악문화예술과",
          "type": "과",
          "name": "국악문화예술과",
          "level": 2,
          "head_position": "국악문화예술과장",
          "head_grade": "",
          "정원": null,
          "근거조문": "시행규칙",
          "분장사무_원문": "",
          "분장사무_항목": [],
          "키워드_태그": [
            "문화_교육"
          ],
          "children": []
        },
        {
          "id": "33730.행정관광복지국.주민복지과",
          "type": "과",
          "name": "주민복지과",
          "level": 2,
          "head_position": "주민복지과장",
          "head_grade": "",
          "정원": null,
          "근거조문": "시행규칙",
          "분장사무_원문": "",
          "분장사무_항목": [],
          "키워드_태그": [
            "복지"
          ],
          "children": []
        },
        {
          "id": "33730.행정관광복지국.가족행복과",
          "type": "과",
          "name": "가족행복과",
          "level": 2,
          "head_position": "가족행복과장",
          "head_grade": "",
          "정원": null,
          "근거조문": "시행규칙",
          "분장사무_원문": "",
          "분장사무_항목": [],
          "키워드_태그": [],
          "children": []
        },
        {
          "id": "33730.행정관광복지국.민원과",
          "type": "과",
          "name": "민원과",
          "level": 2,
          "head_position": "민원과장",
          "head_grade": "",
          "정원": null,
          "근거조문": "시행규칙",
          "분장사무_원문": "",
          "분장사무_항목": [],
          "키워드_태그": [],
          "children": []
        },
        {
          "id": "33730.행정관광복지국.재무과",
          "type": "과",
          "name": "재무과",
          "level": 2,
          "head_position": "재무과장",
          "head_grade": "",
          "정원": null,
          "근거조문": "시행규칙",
          "분장사무_원문": "",
          "분장사무_항목": [],
          "키워드_태그": [],
          "children": []
        }
      ]
    },
    {
      "id": "33730.농산업건설국",
      "type": "국",
      "name": "농산업건설국",
      "level": 1,
      "head_position": "농산업건설국장",
      "head_grade": "5급",
      "정원": null,
      "근거조문": "조례 제6조",
      "분장사무_원문": "제6조(농산업건설국)① 농산업건설국에 스마트농업과, 과수축산과, 환경과, 산림녹지과, 건설교통과, 재난안전과, 도시건축과를 둔다. <개정 2021.5.31, 2023.5.3.>② 농산업건설국의 분장사무에 관한 사항은 규칙으로 정한다.",
      "분장사무_항목": [
        "농산업건설국에 스마트농업과, 과수축산과, 환경과, 산림녹지과, 건설교통과, 재난안전과, 도시건축과를 둔",
        "농산업건설국의 분장사무에 관한 사항은 규칙으로 정한다."
      ],
      "키워드_태그": [
        "환경",
        "녹지_생태",
        "교통",
        "재난_안전",
        "도시_건축",
        "경제_산업"
      ],
      "children": [
        {
          "id": "33730.농산업건설국.스마트농업과",
          "type": "과",
          "name": "스마트농업과",
          "level": 2,
          "head_position": "스마트농업과장",
          "head_grade": "",
          "정원": null,
          "근거조문": "시행규칙",
          "분장사무_원문": "",
          "분장사무_항목": [],
          "키워드_태그": [
            "경제_산업"
          ],
          "children": []
        },
        {
          "id": "33730.농산업건설국.과수축산과",
          "type": "과",
          "name": "과수축산과",
          "level": 2,
          "head_position": "과수축산과장",
          "head_grade": "",
          "정원": null,
          "근거조문": "시행규칙",
          "분장사무_원문": "",
          "분장사무_항목": [],
          "키워드_태그": [],
          "children": []
        },
        {
          "id": "33730.농산업건설국.환경과",
          "type": "과",
          "name": "환경과",
          "level": 2,
          "head_position": "환경과장",
          "head_grade": "",
          "정원": null,
          "근거조문": "시행규칙",
          "분장사무_원문": "",
          "분장사무_항목": [],
          "키워드_태그": [
            "환경"
          ],
          "children": []
        },
        {
          "id": "33730.농산업건설국.산림녹지과",
          "type": "과",
          "name": "산림녹지과",
          "level": 2,
          "head_position": "산림녹지과장",
          "head_grade": "",
          "정원": null,
          "근거조문": "시행규칙",
          "분장사무_원문": "",
          "분장사무_항목": [],
          "키워드_태그": [
            "녹지_생태"
          ],
          "children": []
        },
        {
          "id": "33730.농산업건설국.건설교통과",
          "type": "과",
          "name": "건설교통과",
          "level": 2,
          "head_position": "건설교통과장",
          "head_grade": "",
          "정원": null,
          "근거조문": "시행규칙",
          "분장사무_원문": "",
          "분장사무_항목": [],
          "키워드_태그": [
            "교통"
          ],
          "children": []
        },
        {
          "id": "33730.농산업건설국.재난안전과",
          "type": "과",
          "name": "재난안전과",
          "level": 2,
          "head_position": "재난안전과장",
          "head_grade": "",
          "정원": null,
          "근거조문": "시행규칙",
          "분장사무_원문": "",
          "분장사무_항목": [],
          "키워드_태그": [
            "재난_안전"
          ],
          "children": []
        },
        {
          "id": "33730.농산업건설국.도시건축과",
          "type": "과",
          "name": "도시건축과",
          "level": 2,
          "head_position": "도시건축과장",
          "head_grade": "",
          "정원": null,
          "근거조문": "시행규칙",
          "분장사무_원문": "",
          "분장사무_항목": [],
          "키워드_태그": [
            "도시_건축"
          ],
          "children": []
        }
      ]
    },
    {
      "id": "33730.직속기관.보건소ㆍ보건지소ㆍ보건진료소",
      "type": "직속기관",
      "name": "보건소ㆍ보건지소ㆍ보건진료소",
      "level": 1,
      "head_position": "보건소ㆍ보건지소ㆍ보건진료소장",
      "head_grade": "",
      "정원": null,
      "근거조문": "조례 제7조",
      "분장사무_원문": "제9조(소관사무)① 보건소장은 「지역보건법」 제11조에 따른 소관사무를 수행한다. <개정 2024.5.7.>② 보건진료 전담공무원은 관할구역 안에서 「농어촌 등 보건의료를 위한 특별조치법 시행령」 제14조에 따른 소관사무를 수행한다.③ 보건소장의 분장사무에 관한 사항은 규칙으로 정한다.",
      "분장사무_항목": [
        "보건소장의 분장사무에 관한 사항은 규칙으로 정한다."
      ],
      "키워드_태그": [
        "보건_위생"
      ],
      "children": []
    },
    {
      "id": "33730.직속기관.농업기술센터",
      "type": "직속기관",
      "name": "농업기술센터",
      "level": 1,
      "head_position": "농업기술센터장",
      "head_grade": "",
      "정원": null,
      "근거조문": "조례 제10조",
      "분장사무_원문": "제12조(소관사무) 소장의 분장사무에 관한 사항은 규칙으로 정한다.",
      "분장사무_항목": [],
      "키워드_태그": [
        "경제_산업",
        "문화_교육"
      ],
      "children": []
    },
    {
      "id": "33730.사업소.사업소",
      "type": "사업소",
      "name": "사업소",
      "level": 1,
      "head_position": "사업소장",
      "head_grade": "",
      "정원": null,
      "근거조문": "조례 제13조",
      "분장사무_원문": "제15조(소관사무) 사업소별 소장의 분장사무에 관한 사항은 규칙으로 정한다.",
      "분장사무_항목": [],
      "키워드_태그": [],
      "children": []
    }
  ],
  "validation": {
    "정원_합산_일치": null,
    "정원_총_조례기준": 743,
    "분장사무_누락_부서": [],
    "비고": []
  }
}