{
  "region": {
    "code": "35780",
    "name": "전북특별자치도 부안군",
    "level": "기초",
    "type": "군",
    "parent": "35"
  },
  "source": {
    "ordinance": {
      "name": "부안군 행정기구 설치 조례",
      "mst": "2040127",
      "last_amended": "20250520",
      "url": "https://www.law.go.kr/DRF/lawService.do?OC=open&target=ordin&MST=2040127&type=HTML",
      "fetched_at": "2026-05-09"
    },
    "enforcement_rule": {
      "name": "부안군 행정기구 설치 조례 시행규칙",
      "mst": "2067167",
      "last_amended": "20250915",
      "url": "https://www.law.go.kr/DRF/lawService.do?OC=open&target=ordin&MST=2067167&type=HTML",
      "fetched_at": "2026-05-09"
    },
    "staff_ordinance": {
      "name": "부안군 지방공무원 정원 조례",
      "mst": "1990665",
      "last_amended": "20250101",
      "fetched_at": "2026-05-09"
    }
  },
  "totals": {
    "정원_총": 857,
    "정원_근거조문": "부안군 지방공무원 정원 조례 제2조",
    "정원_비고": ""
  },
  "structure": [
    {
      "id": "35780.관광복지국",
      "type": "국",
      "name": "관광복지국",
      "level": 1,
      "head_position": "관광복지국장",
      "head_grade": "",
      "정원": null,
      "근거조문": "조례 제5조",
      "분장사무_원문": "제5조(관광복지국에 두는 과)① 관광복지국에 관광과, 문화예술과, 교육청소년과, 사회복지과, 재무과, 민원과, 산림정원과를 둔다.② 관광복지국장은 다음 사무를 분장한다.1. 관광정책ㆍ관광산업ㆍ관광기획에 관한 사항2. 관광상품 개발ㆍ관광마케팅ㆍ마이스 산업에 관한 사항3. 축제 개최ㆍ개발에 관한 사항4. 관광지ㆍ관광자원 개발에 관한 사항5. 영상세트장 등 시설 운영ㆍ관리에 관한 사항6. 식품ㆍ공중위생사업에 관한 사항7. 문화예술ㆍ국가유산 관리ㆍ문화콘텐츠에 관한 사항 <개정 2025. 5. 20.>8. 동학농민혁명 정신 계승ㆍ선양 업무에 관한 사항9. 청자박물관ㆍ무형문화재 종합전수교육관에 관한 사항10. 도서관문화시설에 관한 사항11. 교육지원ㆍ평생교육ㆍ노인여성회관에 관한 사항12. 양성평등ㆍ여성복지ㆍ다문화가족ㆍ청소년ㆍ보육ㆍ드림스타트에 관한 사항13. 부안청소년수련원ㆍ부안청림천문대ㆍ부안누에타운에 관한 사항14. 아동복지, 세계스카우트잼버리에 관한 사항15. 주민생활지원서비스 종합계획 수립ㆍ조정에 관한 사항16. 지역사회복지계획 수립ㆍ협의체 운영에 관한 사항17. 기초생활보장ㆍ통합조사ㆍ차상위계층에 관한 사항18. 사회복지시설 설치ㆍ관리에 관한 사항19. 어르신 복지ㆍ장묘ㆍ장사업무에 관한 사항20. 장애인ㆍ의료급여ㆍ의료보호ㆍ보훈에 관한 사항21. 지방세 부과, 세무조사 등 세무행정에 관한 사항22. 지방세 체납징수, 자금관리, 세외수입 운영 및 총괄관리 등에 관한 사항23. 입찰ㆍ계약ㆍ지출 등 회계에 관한 사항24. 국공유재산ㆍ청사ㆍ공용차량 등 재산관리에 관한 사항25. 공공시설 신축 등에 관한 사항26. 민원업무에 관한 사항27. 인감ㆍ주민등록ㆍ가족관계등록에 관한 사항28. 지적관련 민원 및 지적공부의 관리에 관한 사항29. 지적측량정보ㆍ도로명주소ㆍ공간정보에 관한 사항30. 개별공시지가ㆍ부동산실명제 등 토지관리에 관한 사항31. 건축 인허가ㆍ건축물 관리 등 건축에 관한 사항32. 공동주택관리ㆍ주거환경ㆍ주거복지에 관한 사항33. 산림정책ㆍ산림보호ㆍ산림경영에 관한 사항34. 산지이용ㆍ전용, 산림소득에 관한 사항35. 도시공원, 가로수 및 조경, 산림휴양에 관한 사항36. 지방정원조성ㆍ줄포만 갯벌생태공원에 관한 사항",
      "분장사무_항목": [
        "관광정책ㆍ관광산업ㆍ관광기획에 관한 사항",
        "관광상품 개발ㆍ관광마케팅ㆍ마이스 산업에 관한 사항",
        "축제 개최ㆍ개발에 관한 사항",
        "관광지ㆍ관광자원 개발에 관한 사항",
        "영상세트장 등 시설 운영ㆍ관리에 관한 사항",
        "식품ㆍ공중위생사업에 관한 사항",
        "문화예술ㆍ국가유산 관리ㆍ문화콘텐츠에 관한 사항",
        "동학농민혁명 정신 계승ㆍ선양 업무에 관한 사항",
        "청자박물관ㆍ무형문화재 종합전수교육관에 관한 사항",
        "도서관문화시설에 관한 사항",
        "교육지원ㆍ평생교육ㆍ노인여성회관에 관한 사항",
        "양성평등ㆍ여성복지ㆍ다문화가족ㆍ청소년ㆍ보육ㆍ드림스타트에 관한 사항",
        "부안청소년수련원ㆍ부안청림천문대ㆍ부안누에타운에 관한 사항",
        "아동복지, 세계스카우트잼버리에 관한 사항",
        "주민생활지원서비스 종합계획 수립ㆍ조정에 관한 사항",
        "지역사회복지계획 수립ㆍ협의체 운영에 관한 사항",
        "기초생활보장ㆍ통합조사ㆍ차상위계층에 관한 사항",
        "사회복지시설 설치ㆍ관리에 관한 사항",
        "어르신 복지ㆍ장묘ㆍ장사업무에 관한 사항",
        "장애인ㆍ의료급여ㆍ의료보호ㆍ보훈에 관한 사항",
        "지방세 부과, 세무조사 등 세무행정에 관한 사항",
        "지방세 체납징수, 자금관리, 세외수입 운영 및 총괄관리 등에 관한 사항",
        "입찰ㆍ계약ㆍ지출 등 회계에 관한 사항",
        "국공유재산ㆍ청사ㆍ공용차량 등 재산관리에 관한 사항",
        "공공시설 신축 등에 관한 사항",
        "민원업무에 관한 사항",
        "인감ㆍ주민등록ㆍ가족관계등록에 관한 사항",
        "지적관련 민원 및 지적공부의 관리에 관한 사항",
        "지적측량정보ㆍ도로명주소ㆍ공간정보에 관한 사항",
        "개별공시지가ㆍ부동산실명제 등 토지관리에 관한 사항",
        "건축 인허가ㆍ건축물 관리 등 건축에 관한 사항",
        "공동주택관리ㆍ주거환경ㆍ주거복지에 관한 사항",
        "산림정책ㆍ산림보호ㆍ산림경영에 관한 사항",
        "산지이용ㆍ전용, 산림소득에 관한 사항",
        "도시공원, 가로수 및 조경, 산림휴양에 관한 사항",
        "지방정원조성ㆍ줄포만 갯벌생태공원에 관한 사항"
      ],
      "키워드_태그": [
        "환경",
        "녹지_생태",
        "교통",
        "복지",
        "도시_건축",
        "경제_산업",
        "행정_기획",
        "문화_교육",
        "보건_위생"
      ],
      "children": [
        {
          "id": "35780.관광복지국.관광과",
          "type": "과",
          "name": "관광과",
          "level": 2,
          "head_position": "관광과장",
          "head_grade": "",
          "정원": null,
          "근거조문": "조례",
          "분장사무_원문": "",
          "분장사무_항목": [],
          "키워드_태그": [
            "경제_산업"
          ],
          "children": []
        },
        {
          "id": "35780.관광복지국.문화예술과",
          "type": "과",
          "name": "문화예술과",
          "level": 2,
          "head_position": "문화예술과장",
          "head_grade": "",
          "정원": null,
          "근거조문": "조례",
          "분장사무_원문": "",
          "분장사무_항목": [],
          "키워드_태그": [
            "문화_교육"
          ],
          "children": []
        },
        {
          "id": "35780.관광복지국.교육청소년과",
          "type": "과",
          "name": "교육청소년과",
          "level": 2,
          "head_position": "교육청소년과장",
          "head_grade": "",
          "정원": null,
          "근거조문": "조례",
          "분장사무_원문": "",
          "분장사무_항목": [],
          "키워드_태그": [
            "문화_교육"
          ],
          "children": []
        },
        {
          "id": "35780.관광복지국.사회복지과",
          "type": "과",
          "name": "사회복지과",
          "level": 2,
          "head_position": "사회복지과장",
          "head_grade": "",
          "정원": null,
          "근거조문": "조례",
          "분장사무_원문": "",
          "분장사무_항목": [],
          "키워드_태그": [
            "복지"
          ],
          "children": []
        },
        {
          "id": "35780.관광복지국.재무과",
          "type": "과",
          "name": "재무과",
          "level": 2,
          "head_position": "재무과장",
          "head_grade": "",
          "정원": null,
          "근거조문": "조례",
          "분장사무_원문": "",
          "분장사무_항목": [],
          "키워드_태그": [],
          "children": []
        },
        {
          "id": "35780.관광복지국.민원과",
          "type": "과",
          "name": "민원과",
          "level": 2,
          "head_position": "민원과장",
          "head_grade": "",
          "정원": null,
          "근거조문": "조례",
          "분장사무_원문": "",
          "분장사무_항목": [],
          "키워드_태그": [],
          "children": []
        },
        {
          "id": "35780.관광복지국.산림정원과",
          "type": "과",
          "name": "산림정원과",
          "level": 2,
          "head_position": "산림정원과장",
          "head_grade": "",
          "정원": null,
          "근거조문": "조례",
          "분장사무_원문": "",
          "분장사무_항목": [],
          "키워드_태그": [
            "녹지_생태"
          ],
          "children": []
        }
      ]
    },
    {
      "id": "35780.경제산업국",
      "type": "국",
      "name": "경제산업국",
      "level": 1,
      "head_position": "경제산업국장",
      "head_grade": "",
      "정원": null,
      "근거조문": "조례 제6조",
      "분장사무_원문": "제6조(경제산업국에 두는 과)① 경제산업국에 지역경제과, 농업정책과, 농촌활력과, 축산과, 해양수산과, 환경과, 새만금도시과, 건설교통과, 안전총괄과를 둔다.② 경제산업국장은 다음 사무를 분장한다.1. 미래산업기획ㆍ과학기술ㆍICT산업기반ㆍ디지털융합에 관한 사항2. 에너지정책ㆍ신에너지ㆍ재생에너지ㆍ수소산업ㆍ에너지관리에 관한 사항3. 자동차산업ㆍ조선산업ㆍ뿌리기계ㆍ항공해양산업에 관한 사항4. 탄소정책ㆍ탄소소재산업ㆍ바이오헬스산업ㆍ바이오융합산업에 관한 사항5. 기업유치ㆍ기업지원ㆍ투자유치에 관한 사항6. 산업ㆍ농공단지 조성 및 관리에 관한 사항7. 민생경제ㆍ소상공인ㆍ지역상권ㆍ시장에 관한 사항8. 일자리창출ㆍ창업지원ㆍ취업지원에 관한 사항9. 사회적경제정책ㆍ사회적경제육성에 관한 사항10. 청년정책에 관한 사항11. 농정기획ㆍ농지관리ㆍ농정협력에 관한 사항12. 양정ㆍ수도작ㆍ친환경농업ㆍ식량산업ㆍ농민소득안정에 관한 사항13. 스마트 원예에 관한 사항14. 푸드플랜ㆍ로컬푸드ㆍ농산물 유통 및 마케팅에 관한 사항15. 농촌활력ㆍ농촌융복합ㆍ농촌개발에 관한 사항16. 축산정책ㆍ축산경영ㆍ축사환경 개선에 관한 사항17. 동물방역정책ㆍ축산물 위생ㆍ동물복지에 관한 사항18. 수산정책ㆍ어업자원ㆍ수산물가공유통에 관한 사항19. 해양환경ㆍ해양관광ㆍ도서연안개발에 관한 사항20. 어촌ㆍ어항개발 활성화에 관한 사항21. 환경보전ㆍ탄소중립ㆍ기후변화대응ㆍ생태자원에 관한 사항22. 생활환경ㆍ미세먼지대응ㆍ환경관리ㆍ환경민원에 관한 사항23. 폐기물관리ㆍ축산폐수 관리에 관한 사항24. 새만금기획ㆍ새만금개발지원ㆍ새만금관광에 관한 사항25. 도시계획ㆍ개발행위허가ㆍ도시재생ㆍ도시계획도로에 관한 사항26. 건설행정ㆍ도로관리ㆍ도로시설에 관한 사항27. 교통행정ㆍ운수ㆍ차량등록에 관한 사항28. 농업기반조성에 관한 사항29. 안전총괄ㆍ민방위ㆍ생활안전에 관한 사항30. 재난관리ㆍ재해예방ㆍ재해복구ㆍ중대재해에 관한 사항",
      "분장사무_항목": [
        "미래산업기획ㆍ과학기술ㆍICT산업기반ㆍ디지털융합에 관한 사항",
        "에너지정책ㆍ신에너지ㆍ재생에너지ㆍ수소산업ㆍ에너지관리에 관한 사항",
        "자동차산업ㆍ조선산업ㆍ뿌리기계ㆍ항공해양산업에 관한 사항",
        "탄소정책ㆍ탄소소재산업ㆍ바이오헬스산업ㆍ바이오융합산업에 관한 사항",
        "기업유치ㆍ기업지원ㆍ투자유치에 관한 사항",
        "산업ㆍ농공단지 조성 및 관리에 관한 사항",
        "민생경제ㆍ소상공인ㆍ지역상권ㆍ시장에 관한 사항",
        "일자리창출ㆍ창업지원ㆍ취업지원에 관한 사항",
        "사회적경제정책ㆍ사회적경제육성에 관한 사항",
        "청년정책에 관한 사항",
        "농정기획ㆍ농지관리ㆍ농정협력에 관한 사항",
        "양정ㆍ수도작ㆍ친환경농업ㆍ식량산업ㆍ농민소득안정에 관한 사항",
        "스마트 원예에 관한 사항",
        "푸드플랜ㆍ로컬푸드ㆍ농산물 유통 및 마케팅에 관한 사항",
        "농촌활력ㆍ농촌융복합ㆍ농촌개발에 관한 사항",
        "축산정책ㆍ축산경영ㆍ축사환경 개선에 관한 사항",
        "동물방역정책ㆍ축산물 위생ㆍ동물복지에 관한 사항",
        "수산정책ㆍ어업자원ㆍ수산물가공유통에 관한 사항",
        "해양환경ㆍ해양관광ㆍ도서연안개발에 관한 사항",
        "어촌ㆍ어항개발 활성화에 관한 사항",
        "환경보전ㆍ탄소중립ㆍ기후변화대응ㆍ생태자원에 관한 사항",
        "생활환경ㆍ미세먼지대응ㆍ환경관리ㆍ환경민원에 관한 사항",
        "폐기물관리ㆍ축산폐수 관리에 관한 사항",
        "새만금기획ㆍ새만금개발지원ㆍ새만금관광에 관한 사항",
        "도시계획ㆍ개발행위허가ㆍ도시재생ㆍ도시계획도로에 관한 사항",
        "건설행정ㆍ도로관리ㆍ도로시설에 관한 사항",
        "교통행정ㆍ운수ㆍ차량등록에 관한 사항",
        "농업기반조성에 관한 사항",
        "안전총괄ㆍ민방위ㆍ생활안전에 관한 사항",
        "재난관리ㆍ재해예방ㆍ재해복구ㆍ중대재해에 관한 사항"
      ],
      "키워드_태그": [
        "기후",
        "환경",
        "에너지",
        "녹지_생태",
        "교통",
        "복지",
        "재난_안전",
        "도시_건축",
        "경제_산업",
        "행정_기획",
        "보건_위생"
      ],
      "children": [
        {
          "id": "35780.경제산업국.지역경제과",
          "type": "과",
          "name": "지역경제과",
          "level": 2,
          "head_position": "지역경제과장",
          "head_grade": "",
          "정원": null,
          "근거조문": "조례",
          "분장사무_원문": "",
          "분장사무_항목": [],
          "키워드_태그": [
            "경제_산업"
          ],
          "children": []
        },
        {
          "id": "35780.경제산업국.농업정책과",
          "type": "과",
          "name": "농업정책과",
          "level": 2,
          "head_position": "농업정책과장",
          "head_grade": "",
          "정원": null,
          "근거조문": "조례",
          "분장사무_원문": "",
          "분장사무_항목": [],
          "키워드_태그": [
            "경제_산업"
          ],
          "children": []
        },
        {
          "id": "35780.경제산업국.농촌활력과",
          "type": "과",
          "name": "농촌활력과",
          "level": 2,
          "head_position": "농촌활력과장",
          "head_grade": "",
          "정원": null,
          "근거조문": "조례",
          "분장사무_원문": "",
          "분장사무_항목": [],
          "키워드_태그": [],
          "children": []
        },
        {
          "id": "35780.경제산업국.축산과",
          "type": "과",
          "name": "축산과",
          "level": 2,
          "head_position": "축산과장",
          "head_grade": "",
          "정원": null,
          "근거조문": "조례",
          "분장사무_원문": "",
          "분장사무_항목": [],
          "키워드_태그": [],
          "children": []
        },
        {
          "id": "35780.경제산업국.해양수산과",
          "type": "과",
          "name": "해양수산과",
          "level": 2,
          "head_position": "해양수산과장",
          "head_grade": "",
          "정원": null,
          "근거조문": "조례",
          "분장사무_원문": "",
          "분장사무_항목": [],
          "키워드_태그": [],
          "children": []
        },
        {
          "id": "35780.경제산업국.환경과",
          "type": "과",
          "name": "환경과",
          "level": 2,
          "head_position": "환경과장",
          "head_grade": "",
          "정원": null,
          "근거조문": "조례",
          "분장사무_원문": "",
          "분장사무_항목": [],
          "키워드_태그": [
            "환경"
          ],
          "children": []
        },
        {
          "id": "35780.경제산업국.새만금도시과",
          "type": "과",
          "name": "새만금도시과",
          "level": 2,
          "head_position": "새만금도시과장",
          "head_grade": "",
          "정원": null,
          "근거조문": "조례",
          "분장사무_원문": "",
          "분장사무_항목": [],
          "키워드_태그": [
            "도시_건축"
          ],
          "children": []
        },
        {
          "id": "35780.경제산업국.건설교통과",
          "type": "과",
          "name": "건설교통과",
          "level": 2,
          "head_position": "건설교통과장",
          "head_grade": "",
          "정원": null,
          "근거조문": "조례",
          "분장사무_원문": "",
          "분장사무_항목": [],
          "키워드_태그": [
            "교통"
          ],
          "children": []
        },
        {
          "id": "35780.경제산업국.안전총괄과",
          "type": "과",
          "name": "안전총괄과",
          "level": 2,
          "head_position": "안전총괄과장",
          "head_grade": "",
          "정원": null,
          "근거조문": "조례",
          "분장사무_원문": "",
          "분장사무_항목": [],
          "키워드_태그": [
            "재난_안전"
          ],
          "children": []
        }
      ]
    },
    {
      "id": "35780.담당관",
      "type": "관",
      "name": "담당관",
      "level": 1,
      "head_position": "담당관",
      "head_grade": "",
      "정원": null,
      "근거조문": "조례",
      "분장사무_원문": "",
      "분장사무_항목": [],
      "키워드_태그": [],
      "children": [
        {
          "id": "35780.담당관.기획감사담당관",
          "type": "담당관",
          "name": "기획감사담당관",
          "level": 2,
          "head_position": "기획감사담당관",
          "head_grade": "",
          "정원": null,
          "근거조문": "조례",
          "분장사무_원문": "",
          "분장사무_항목": [],
          "키워드_태그": [
            "행정_기획"
          ],
          "children": []
        },
        {
          "id": "35780.담당관.자치행정담당관",
          "type": "담당관",
          "name": "자치행정담당관",
          "level": 2,
          "head_position": "자치행정담당관",
          "head_grade": "",
          "정원": null,
          "근거조문": "조례",
          "분장사무_원문": "",
          "분장사무_항목": [],
          "키워드_태그": [],
          "children": []
        }
      ]
    },
    {
      "id": "35780.직속기관.보건소ㆍ보건지소ㆍ보건진료소",
      "type": "직속기관",
      "name": "보건소ㆍ보건지소ㆍ보건진료소",
      "level": 1,
      "head_position": "보건소ㆍ보건지소ㆍ보건진료소장",
      "head_grade": "",
      "정원": null,
      "근거조문": "조례 제7조",
      "분장사무_원문": "",
      "분장사무_항목": [],
      "키워드_태그": [
        "보건_위생"
      ],
      "children": []
    },
    {
      "id": "35780.직속기관.농업기술센터",
      "type": "직속기관",
      "name": "농업기술센터",
      "level": 1,
      "head_position": "농업기술센터장",
      "head_grade": "",
      "정원": null,
      "근거조문": "조례 제17조",
      "분장사무_원문": "제16조(소관사무) 각 사업소별 소장이 관장하는 사무는 다음 각 호와 같다.1. 상하수도사업소가. 상ㆍ하수도 사업계획 수립 및 시행에 관한 사항나. 상수원보호구역 및 상수도 관리에 관한 사항다. 지하수개발이용에 관한 사항라. 농어촌마을 하수도사업 및 하수도 관리에 관한 사항마. 하천계획ㆍ하천관리에 관한 사항2. 환경사업소가. 환경기초시설 설치ㆍ운영관리나. 청소 총괄ㆍ생활폐기물 관리에 관한 사항3. 문화체육시설사업소가. 예술회관 운영에 관한 사항나. 체육진흥 종합대책 수립ㆍ시행에 관한 사항다. 문화ㆍ체육시설 확충 및 유지관리에 관한 사항라. 스포츠 행사유치ㆍ지원 등 스포츠산업에 관한 사항",
      "분장사무_항목": [
        "상하수도사업소",
        "상ㆍ하수도 사업계획 수립 및 시행에 관한 사항",
        "상수원보호구역 및 상수도 관리에 관한 사항",
        "지하수개발이용에 관한 사항",
        "농어촌마을 하수도사업 및 하수도 관리에 관한 사항",
        "하천계획ㆍ하천관리에 관한 사항",
        "환경사업소",
        "환경기초시설 설치ㆍ운영관리",
        "청소 총괄ㆍ생활폐기물 관리에 관한 사항",
        "문화체육시설사업소",
        "예술회관 운영에 관한 사항",
        "체육진흥 종합대책 수립ㆍ시행에 관한 사항",
        "문화ㆍ체육시설 확충 및 유지관리에 관한 사항",
        "스포츠 행사유치ㆍ지원 등 스포츠산업에 관한 사항"
      ],
      "키워드_태그": [
        "환경",
        "도시_건축",
        "경제_산업",
        "문화_교육"
      ],
      "children": []
    }
  ],
  "validation": {
    "정원_합산_일치": null,
    "정원_총_조례기준": 857,
    "분장사무_누락_부서": [
      "담당관"
    ],
    "비고": []
  }
}